colorTetris/source/t01_ai_ofm.sv
`default_nettype none 
module t01_ai_ofm (
    input logic clk, rst, mmu_done,
    input logic [17:0] n_mmu_result,
    input logic [3:0] n_blockX, 
    input logic [4:0] n_block_type, 
    output logic [3:0] blockX, 
    output logic [4:0] block_type,  
    output logic done
); 
    logic [4:0] c_block_type;
    logic [3:0] c_blockX;  
    logic [17:0] c_mmu_result; 
    logic testing; 
    assign testing = n_mmu_result > c_mmu_result; 

    // assign block_type = c_block_type; 
    // assign blockX = c_blockX; 

    always_ff @(posedge clk, posedge rst) begin 
        if (rst) begin 
            c_mmu_result <= 0; 
            block_type <= 0;
            blockX <= 0;
            done <= 0;  
        end else if (mmu_done) begin 
            if (n_mmu_result > c_mmu_result) begin 
                c_mmu_result <= n_mmu_result; 
                blockX <= n_blockX; 
                block_type <= n_block_type; 
            end
            done <= 1'b1; 
        end
    end 
endmodule

colorTetris/testbench/t01_ai_ofm_tb.sv
`timescale 1us/1ps
module t01_ai_ofm_tb; 
    logic clk, rst;
    logic mmu_done; 
    logic [17:0] n_mmu_result; 
    logic [3:0] n_blockX; 
    logic [4:0] n_block_type; 
    logic [3:0] blockX; 
    logic [4:0] block_type; 
    logic done; 
     
   
    t01_ai_ofm ge (.clk(clk), .rst(rst), .mmu_done(mmu_done), .n_mmu_result(n_mmu_result), .n_blockX(n_blockX), .n_block_type(n_block_type), .blockX(blockX), .block_type(block_type), .done(done)); 

    task tog_rst; 
        rst = 1; #1; 
        rst = 0; 
    endtask 

    initial clk = 0; 
    always clk = #1 ~clk; 

 
    initial begin 
        $dumpfile("waves/t01_ai_ofm.vcd"); 
        $dumpvars(0, t01_ai_ofm_tb);

        n_blockX = 'd7; 
        n_block_type = 'd3; 
        mmu_done = 1'b1; 
        tog_rst(); 
            for (int i = 0; i <= 'd10; i++) begin 
                for (int j = 0; j <= 'd7; j++) begin 
                    for (int k = 0; k <= 'd9; k++) begin 
                        if (i == 'd5) begin 
                            n_mmu_result = 'd0; 
                        end else begin 
                            n_mmu_result = i[17:0];
                        end  
                        n_block_type = j[4:0]; 
                        n_blockX = k[3:0]; 
                        #1; 
                    end
                end
            end

    #1 $finish; 
    end
endmodule

colorTetris/waves/t01_ai_ofm.vcd
$date
	Sat Aug  2 15:26:49 2025
$end
$version
	Icarus Verilog
$end
$timescale
	1ps
$end
$scope module t01_ai_ofm_tb $end
$var wire 1 ! done $end
$var wire 5 " block_type [4:0] $end
$var wire 4 # blockX [3:0] $end
$var reg 1 $ clk $end
$var reg 1 % mmu_done $end
$var reg 4 & n_blockX [3:0] $end
$var reg 5 ' n_block_type [4:0] $end
$var reg 18 ( n_mmu_result [17:0] $end
$var reg 1 ) rst $end
$scope module ge $end
$var wire 1 $ clk $end
$var wire 1 % mmu_done $end
$var wire 4 * n_blockX [3:0] $end
$var wire 5 + n_block_type [4:0] $end
$var wire 18 , n_mmu_result [17:0] $end
$var wire 1 ) rst $end
$var wire 1 - testing $end
$var reg 4 . blockX [3:0] $end
$var reg 5 / block_type [4:0] $end
$var reg 18 0 c_mmu_result [17:0] $end
$var reg 1 ! done $end
$upscope $end
$scope begin $ivl_for_loop0 $end
$var integer 32 1 i [31:0] $end
$scope begin $ivl_for_loop1 $end
$var integer 32 2 j [31:0] $end
$scope begin $ivl_for_loop2 $end
$var integer 32 3 k [31:0] $end
$upscope $end
$upscope $end
$upscope $end
$scope task tog_rst $end
$upscope $end
$upscope $end
$enddefinitions $end
$comment Show the parameter values. $end
$dumpall
$end
#0
$dumpvars
b0 3
b0 2
b0 1
b0 0
b0 /
b0 .
x-
bx ,
b11 +
b111 *
1)
bx (
b11 '
b111 &
1%
0$
b0 #
b0 "
0!
$end
#1000000
1!
b0 &
b0 *
b0 '
b0 +
0-
b0 (
b0 ,
0)
1$
#2000000
b1 &
b1 *
b1 3
0$
#3000000
b10 &
b10 *
b10 3
1$
#4000000
b11 &
b11 *
b11 3
0$
#5000000
b100 &
b100 *
b100 3
1$
#6000000
b101 &
b101 *
b101 3
0$
#7000000
b110 &
b110 *
b110 3
1$
#8000000
b111 &
b111 *
b111 3
0$
#9000000
b1000 &
b1000 *
b1000 3
1$
#10000000
b1001 &
b1001 *
b1001 3
0$
#11000000
b0 &
b0 *
b1 '
b1 +
b1 2
b0 3
1$
#12000000
b1 &
b1 *
b1 3
0$
#13000000
b10 &
b10 *
b10 3
1$
#14000000
b11 &
b11 *
b11 3
0$
#15000000
b100 &
b100 *
b100 3
1$
#16000000
b101 &
b101 *
b101 3
0$
#17000000
b110 &
b110 *
b110 3
1$
#18000000
b111 &
b111 *
b111 3
0$
#19000000
b1000 &
b1000 *
b1000 3
1$
#20000000
b1001 &
b1001 *
b1001 3
0$
#21000000
b0 &
b0 *
b10 '
b10 +
b10 2
b0 3
1$
#22000000
b1 &
b1 *
b1 3
0$
#23000000
b10 &
b10 *
b10 3
1$
#24000000
b11 &
b11 *
b11 3
0$
#25000000
b100 &
b100 *
b100 3
1$
#26000000
b101 &
b101 *
b101 3
0$
#27000000
b110 &
b110 *
b110 3
1$
#28000000
b111 &
b111 *
b111 3
0$
#29000000
b1000 &
b1000 *
b1000 3
1$
#30000000
b1001 &
b1001 *
b1001 3
0$
#31000000
b0 &
b0 *
b11 '
b11 +
b11 2
b0 3
1$
#32000000
b1 &
b1 *
b1 3
0$
#33000000
b10 &
b10 *
b10 3
1$
#34000000
b11 &
b11 *
b11 3
0$
#35000000
b100 &
b100 *
b100 3
1$
#36000000
b101 &
b101 *
b101 3
0$
#37000000
b110 &
b110 *
b110 3
1$
#38000000
b111 &
b111 *
b111 3
0$
#39000000
b1000 &
b1000 *
b1000 3
1$
#40000000
b1001 &
b1001 *
b1001 3
0$
#41000000
b0 &
b0 *
b100 '
b100 +
b100 2
b0 3
1$
#42000000
b1 &
b1 *
b1 3
0$
#43000000
b10 &
b10 *
b10 3
1$
#44000000
b11 &
b11 *
b11 3
0$
#45000000
b100 &
b100 *
b100 3
1$
#46000000
b101 &
b101 *
b101 3
0$
#47000000
b110 &
b110 *
b110 3
1$
#48000000
b111 &
b111 *
b111 3
0$
#49000000
b1000 &
b1000 *
b1000 3
1$
#50000000
b1001 &
b1001 *
b1001 3
0$
#51000000
b0 &
b0 *
b101 '
b101 +
b101 2
b0 3
1$
#52000000
b1 &
b1 *
b1 3
0$
#53000000
b10 &
b10 *
b10 3
1$
#54000000
b11 &
b11 *
b11 3
0$
#55000000
b100 &
b100 *
b100 3
1$
#56000000
b101 &
b101 *
b101 3
0$
#57000000
b110 &
b110 *
b110 3
1$
#58000000
b111 &
b111 *
b111 3
0$
#59000000
b1000 &
b1000 *
b1000 3
1$
#60000000
b1001 &
b1001 *
b1001 3
0$
#61000000
b0 &
b0 *
b110 '
b110 +
b110 2
b0 3
1$
#62000000
b1 &
b1 *
b1 3
0$
#63000000
b10 &
b10 *
b10 3
1$
#64000000
b11 &
b11 *
b11 3
0$
#65000000
b100 &
b100 *
b100 3
1$
#66000000
b101 &
b101 *
b101 3
0$
#67000000
b110 &
b110 *
b110 3
1$
#68000000
b111 &
b111 *
b111 3
0$
#69000000
b1000 &
b1000 *
b1000 3
1$
#70000000
b1001 &
b1001 *
b1001 3
0$
#71000000
b0 &
b0 *
b111 '
b111 +
b111 2
b0 3
1$
#72000000
b1 &
b1 *
b1 3
0$
#73000000
b10 &
b10 *
b10 3
1$
#74000000
b11 &
b11 *
b11 3
0$
#75000000
b100 &
b100 *
b100 3
1$
#76000000
b101 &
b101 *
b101 3
0$
#77000000
b110 &
b110 *
b110 3
1$
#78000000
b111 &
b111 *
b111 3
0$
#79000000
b1000 &
b1000 *
b1000 3
1$
#80000000
b1001 &
b1001 *
b1001 3
0$
#81000000
b1 0
b0 &
b0 *
b0 '
b0 +
0-
b1 (
b1 ,
b1 1
b0 2
b0 3
1$
#82000000
b1 &
b1 *
b1 3
0$
#83000000
b10 &
b10 *
b10 3
1$
#84000000
b11 &
b11 *
b11 3
0$
#85000000
b100 &
b100 *
b100 3
1$
#86000000
b101 &
b101 *
b101 3
0$
#87000000
b110 &
b110 *
b110 3
1$
#88000000
b111 &
b111 *
b111 3
0$
#89000000
b1000 &
b1000 *
b1000 3
1$
#90000000
b1001 &
b1001 *
b1001 3
0$
#91000000
b0 &
b0 *
b1 '
b1 +
b1 2
b0 3
1$
#92000000
b1 &
b1 *
b1 3
0$
#93000000
b10 &
b10 *
b10 3
1$
#94000000
b11 &
b11 *
b11 3
0$
#95000000
b100 &
b100 *
b100 3
1$
#96000000
b101 &
b101 *
b101 3
0$
#97000000
b110 &
b110 *
b110 3
1$
#98000000
b111 &
b111 *
b111 3
0$
#99000000
b1000 &
b1000 *
b1000 3
1$
#100000000
b1001 &
b1001 *
b1001 3
0$
#101000000
b0 &
b0 *
b10 '
b10 +
b10 2
b0 3
1$
#102000000
b1 &
b1 *
b1 3
0$
#103000000
b10 &
b10 *
b10 3
1$
#104000000
b11 &
b11 *
b11 3
0$
#105000000
b100 &
b100 *
b100 3
1$
#106000000
b101 &
b101 *
b101 3
0$
#107000000
b110 &
b110 *
b110 3
1$
#108000000
b111 &
b111 *
b111 3
0$
#109000000
b1000 &
b1000 *
b1000 3
1$
#110000000
b1001 &
b1001 *
b1001 3
0$
#111000000
b0 &
b0 *
b11 '
b11 +
b11 2
b0 3
1$
#112000000
b1 &
b1 *
b1 3
0$
#113000000
b10 &
b10 *
b10 3
1$
#114000000
b11 &
b11 *
b11 3
0$
#115000000
b100 &
b100 *
b100 3
1$
#116000000
b101 &
b101 *
b101 3
0$
#117000000
b110 &
b110 *
b110 3
1$
#118000000
b111 &
b111 *
b111 3
0$
#119000000
b1000 &
b1000 *
b1000 3
1$
#120000000
b1001 &
b1001 *
b1001 3
0$
#121000000
b0 &
b0 *
b100 '
b100 +
b100 2
b0 3
1$
#122000000
b1 &
b1 *
b1 3
0$
#123000000
b10 &
b10 *
b10 3
1$
#124000000
b11 &
b11 *
b11 3
0$
#125000000
b100 &
b100 *
b100 3
1$
#126000000
b101 &
b101 *
b101 3
0$
#127000000
b110 &
b110 *
b110 3
1$
#128000000
b111 &
b111 *
b111 3
0$
#129000000
b1000 &
b1000 *
b1000 3
1$
#130000000
b1001 &
b1001 *
b1001 3
0$
#131000000
b0 &
b0 *
b101 '
b101 +
b101 2
b0 3
1$
#132000000
b1 &
b1 *
b1 3
0$
#133000000
b10 &
b10 *
b10 3
1$
#134000000
b11 &
b11 *
b11 3
0$
#135000000
b100 &
b100 *
b100 3
1$
#136000000
b101 &
b101 *
b101 3
0$
#137000000
b110 &
b110 *
b110 3
1$
#138000000
b111 &
b111 *
b111 3
0$
#139000000
b1000 &
b1000 *
b1000 3
1$
#140000000
b1001 &
b1001 *
b1001 3
0$
#141000000
b0 &
b0 *
b110 '
b110 +
b110 2
b0 3
1$
#142000000
b1 &
b1 *
b1 3
0$
#143000000
b10 &
b10 *
b10 3
1$
#144000000
b11 &
b11 *
b11 3
0$
#145000000
b100 &
b100 *
b100 3
1$
#146000000
b101 &
b101 *
b101 3
0$
#147000000
b110 &
b110 *
b110 3
1$
#148000000
b111 &
b111 *
b111 3
0$
#149000000
b1000 &
b1000 *
b1000 3
1$
#150000000
b1001 &
b1001 *
b1001 3
0$
#151000000
b0 &
b0 *
b111 '
b111 +
b111 2
b0 3
1$
#152000000
b1 &
b1 *
b1 3
0$
#153000000
b10 &
b10 *
b10 3
1$
#154000000
b11 &
b11 *
b11 3
0$
#155000000
b100 &
b100 *
b100 3
1$
#156000000
b101 &
b101 *
b101 3
0$
#157000000
b110 &
b110 *
b110 3
1$
#158000000
b111 &
b111 *
b111 3
0$
#159000000
b1000 &
b1000 *
b1000 3
1$
#160000000
b1001 &
b1001 *
b1001 3
0$
#161000000
b10 0
b0 &
b0 *
b0 '
b0 +
0-
b10 (
b10 ,
b10 1
b0 2
b0 3
1$
#162000000
b1 &
b1 *
b1 3
0$
#163000000
b10 &
b10 *
b10 3
1$
#164000000
b11 &
b11 *
b11 3
0$
#165000000
b100 &
b100 *
b100 3
1$
#166000000
b101 &
b101 *
b101 3
0$
#167000000
b110 &
b110 *
b110 3
1$
#168000000
b111 &
b111 *
b111 3
0$
#169000000
b1000 &
b1000 *
b1000 3
1$
#170000000
b1001 &
b1001 *
b1001 3
0$
#171000000
b0 &
b0 *
b1 '
b1 +
b1 2
b0 3
1$
#172000000
b1 &
b1 *
b1 3
0$
#173000000
b10 &
b10 *
b10 3
1$
#174000000
b11 &
b11 *
b11 3
0$
#175000000
b100 &
b100 *
b100 3
1$
#176000000
b101 &
b101 *
b101 3
0$
#177000000
b110 &
b110 *
b110 3
1$
#178000000
b111 &
b111 *
b111 3
0$
#179000000
b1000 &
b1000 *
b1000 3
1$
#180000000
b1001 &
b1001 *
b1001 3
0$
#181000000
b0 &
b0 *
b10 '
b10 +
b10 2
b0 3
1$
#182000000
b1 &
b1 *
b1 3
0$
#183000000
b10 &
b10 *
b10 3
1$
#184000000
b11 &
b11 *
b11 3
0$
#185000000
b100 &
b100 *
b100 3
1$
#186000000
b101 &
b101 *
b101 3
0$
#187000000
b110 &
b110 *
b110 3
1$
#188000000
b111 &
b111 *
b111 3
0$
#189000000
b1000 &
b1000 *
b1000 3
1$
#190000000
b1001 &
b1001 *
b1001 3
0$
#191000000
b0 &
b0 *
b11 '
b11 +
b11 2
b0 3
1$
#192000000
b1 &
b1 *
b1 3
0$
#193000000
b10 &
b10 *
b10 3
1$
#194000000
b11 &
b11 *
b11 3
0$
#195000000
b100 &
b100 *
b100 3
1$
#196000000
b101 &
b101 *
b101 3
0$
#197000000
b110 &
b110 *
b110 3
1$
#198000000
b111 &
b111 *
b111 3
0$
#199000000
b1000 &
b1000 *
b1000 3
1$
#200000000
b1001 &
b1001 *
b1001 3
0$
#201000000
b0 &
b0 *
b100 '
b100 +
b100 2
b0 3
1$
#202000000
b1 &
b1 *
b1 3
0$
#203000000
b10 &
b10 *
b10 3
1$
#204000000
b11 &
b11 *
b11 3
0$
#205000000
b100 &
b100 *
b100 3
1$
#206000000
b101 &
b101 *
b101 3
0$
#207000000
b110 &
b110 *
b110 3
1$
#208000000
b111 &
b111 *
b111 3
0$
#209000000
b1000 &
b1000 *
b1000 3
1$
#210000000
b1001 &
b1001 *
b1001 3
0$
#211000000
b0 &
b0 *
b101 '
b101 +
b101 2
b0 3
1$
#212000000
b1 &
b1 *
b1 3
0$
#213000000
b10 &
b10 *
b10 3
1$
#214000000
b11 &
b11 *
b11 3
0$
#215000000
b100 &
b100 *
b100 3
1$
#216000000
b101 &
b101 *
b101 3
0$
#217000000
b110 &
b110 *
b110 3
1$
#218000000
b111 &
b111 *
b111 3
0$
#219000000
b1000 &
b1000 *
b1000 3
1$
#220000000
b1001 &
b1001 *
b1001 3
0$
#221000000
b0 &
b0 *
b110 '
b110 +
b110 2
b0 3
1$
#222000000
b1 &
b1 *
b1 3
0$
#223000000
b10 &
b10 *
b10 3
1$
#224000000
b11 &
b11 *
b11 3
0$
#225000000
b100 &
b100 *
b100 3
1$
#226000000
b101 &
b101 *
b101 3
0$
#227000000
b110 &
b110 *
b110 3
1$
#228000000
b111 &
b111 *
b111 3
0$
#229000000
b1000 &
b1000 *
b1000 3
1$
#230000000
b1001 &
b1001 *
b1001 3
0$
#231000000
b0 &
b0 *
b111 '
b111 +
b111 2
b0 3
1$
#232000000
b1 &
b1 *
b1 3
0$
#233000000
b10 &
b10 *
b10 3
1$
#234000000
b11 &
b11 *
b11 3
0$
#235000000
b100 &
b100 *
b100 3
1$
#236000000
b101 &
b101 *
b101 3
0$
#237000000
b110 &
b110 *
b110 3
1$
#238000000
b111 &
b111 *
b111 3
0$
#239000000
b1000 &
b1000 *
b1000 3
1$
#240000000
b1001 &
b1001 *
b1001 3
0$
#241000000
b11 0
b0 &
b0 *
b0 '
b0 +
0-
b11 (
b11 ,
b11 1
b0 2
b0 3
1$
#242000000
b1 &
b1 *
b1 3
0$
#243000000
b10 &
b10 *
b10 3
1$
#244000000
b11 &
b11 *
b11 3
0$
#245000000
b100 &
b100 *
b100 3
1$
#246000000
b101 &
b101 *
b101 3
0$
#247000000
b110 &
b110 *
b110 3
1$
#248000000
b111 &
b111 *
b111 3
0$
#249000000
b1000 &
b1000 *
b1000 3
1$
#250000000
b1001 &
b1001 *
b1001 3
0$
#251000000
b0 &
b0 *
b1 '
b1 +
b1 2
b0 3
1$
#252000000
b1 &
b1 *
b1 3
0$
#253000000
b10 &
b10 *
b10 3
1$
#254000000
b11 &
b11 *
b11 3
0$
#255000000
b100 &
b100 *
b100 3
1$
#256000000
b101 &
b101 *
b101 3
0$
#257000000
b110 &
b110 *
b110 3
1$
#258000000
b111 &
b111 *
b111 3
0$
#259000000
b1000 &
b1000 *
b1000 3
1$
#260000000
b1001 &
b1001 *
b1001 3
0$
#261000000
b0 &
b0 *
b10 '
b10 +
b10 2
b0 3
1$
#262000000
b1 &
b1 *
b1 3
0$
#263000000
b10 &
b10 *
b10 3
1$
#264000000
b11 &
b11 *
b11 3
0$
#265000000
b100 &
b100 *
b100 3
1$
#266000000
b101 &
b101 *
b101 3
0$
#267000000
b110 &
b110 *
b110 3
1$
#268000000
b111 &
b111 *
b111 3
0$
#269000000
b1000 &
b1000 *
b1000 3
1$
#270000000
b1001 &
b1001 *
b1001 3
0$
#271000000
b0 &
b0 *
b11 '
b11 +
b11 2
b0 3
1$
#272000000
b1 &
b1 *
b1 3
0$
#273000000
b10 &
b10 *
b10 3
1$
#274000000
b11 &
b11 *
b11 3
0$
#275000000
b100 &
b100 *
b100 3
1$
#276000000
b101 &
b101 *
b101 3
0$
#277000000
b110 &
b110 *
b110 3
1$
#278000000
b111 &
b111 *
b111 3
0$
#279000000
b1000 &
b1000 *
b1000 3
1$
#280000000
b1001 &
b1001 *
b1001 3
0$
#281000000
b0 &
b0 *
b100 '
b100 +
b100 2
b0 3
1$
#282000000
b1 &
b1 *
b1 3
0$
#283000000
b10 &
b10 *
b10 3
1$
#284000000
b11 &
b11 *
b11 3
0$
#285000000
b100 &
b100 *
b100 3
1$
#286000000
b101 &
b101 *
b101 3
0$
#287000000
b110 &
b110 *
b110 3
1$
#288000000
b111 &
b111 *
b111 3
0$
#289000000
b1000 &
b1000 *
b1000 3
1$
#290000000
b1001 &
b1001 *
b1001 3
0$
#291000000
b0 &
b0 *
b101 '
b101 +
b101 2
b0 3
1$
#292000000
b1 &
b1 *
b1 3
0$
#293000000
b10 &
b10 *
b10 3
1$
#294000000
b11 &
b11 *
b11 3
0$
#295000000
b100 &
b100 *
b100 3
1$
#296000000
b101 &
b101 *
b101 3
0$
#297000000
b110 &
b110 *
b110 3
1$
#298000000
b111 &
b111 *
b111 3
0$
#299000000
b1000 &
b1000 *
b1000 3
1$
#300000000
b1001 &
b1001 *
b1001 3
0$
#301000000
b0 &
b0 *
b110 '
b110 +
b110 2
b0 3
1$
#302000000
b1 &
b1 *
b1 3
0$
#303000000
b10 &
b10 *
b10 3
1$
#304000000
b11 &
b11 *
b11 3
0$
#305000000
b100 &
b100 *
b100 3
1$
#306000000
b101 &
b101 *
b101 3
0$
#307000000
b110 &
b110 *
b110 3
1$
#308000000
b111 &
b111 *
b111 3
0$
#309000000
b1000 &
b1000 *
b1000 3
1$
#310000000
b1001 &
b1001 *
b1001 3
0$
#311000000
b0 &
b0 *
b111 '
b111 +
b111 2
b0 3
1$
#312000000
b1 &
b1 *
b1 3
0$
#313000000
b10 &
b10 *
b10 3
1$
#314000000
b11 &
b11 *
b11 3
0$
#315000000
b100 &
b100 *
b100 3
1$
#316000000
b101 &
b101 *
b101 3
0$
#317000000
b110 &
b110 *
b110 3
1$
#318000000
b111 &
b111 *
b111 3
0$
#319000000
b1000 &
b1000 *
b1000 3
1$
#320000000
b1001 &
b1001 *
b1001 3
0$
#321000000
b100 0
b0 &
b0 *
b0 '
b0 +
0-
b100 (
b100 ,
b100 1
b0 2
b0 3
1$
#322000000
b1 &
b1 *
b1 3
0$
#323000000
b10 &
b10 *
b10 3
1$
#324000000
b11 &
b11 *
b11 3
0$
#325000000
b100 &
b100 *
b100 3
1$
#326000000
b101 &
b101 *
b101 3
0$
#327000000
b110 &
b110 *
b110 3
1$
#328000000
b111 &
b111 *
b111 3
0$
#329000000
b1000 &
b1000 *
b1000 3
1$
#330000000
b1001 &
b1001 *
b1001 3
0$
#331000000
b0 &
b0 *
b1 '
b1 +
b1 2
b0 3
1$
#332000000
b1 &
b1 *
b1 3
0$
#333000000
b10 &
b10 *
b10 3
1$
#334000000
b11 &
b11 *
b11 3
0$
#335000000
b100 &
b100 *
b100 3
1$
#336000000
b101 &
b101 *
b101 3
0$
#337000000
b110 &
b110 *
b110 3
1$
#338000000
b111 &
b111 *
b111 3
0$
#339000000
b1000 &
b1000 *
b1000 3
1$
#340000000
b1001 &
b1001 *
b1001 3
0$
#341000000
b0 &
b0 *
b10 '
b10 +
b10 2
b0 3
1$
#342000000
b1 &
b1 *
b1 3
0$
#343000000
b10 &
b10 *
b10 3
1$
#344000000
b11 &
b11 *
b11 3
0$
#345000000
b100 &
b100 *
b100 3
1$
#346000000
b101 &
b101 *
b101 3
0$
#347000000
b110 &
b110 *
b110 3
1$
#348000000
b111 &
b111 *
b111 3
0$
#349000000
b1000 &
b1000 *
b1000 3
1$
#350000000
b1001 &
b1001 *
b1001 3
0$
#351000000
b0 &
b0 *
b11 '
b11 +
b11 2
b0 3
1$
#352000000
b1 &
b1 *
b1 3
0$
#353000000
b10 &
b10 *
b10 3
1$
#354000000
b11 &
b11 *
b11 3
0$
#355000000
b100 &
b100 *
b100 3
1$
#356000000
b101 &
b101 *
b101 3
0$
#357000000
b110 &
b110 *
b110 3
1$
#358000000
b111 &
b111 *
b111 3
0$
#359000000
b1000 &
b1000 *
b1000 3
1$
#360000000
b1001 &
b1001 *
b1001 3
0$
#361000000
b0 &
b0 *
b100 '
b100 +
b100 2
b0 3
1$
#362000000
b1 &
b1 *
b1 3
0$
#363000000
b10 &
b10 *
b10 3
1$
#364000000
b11 &
b11 *
b11 3
0$
#365000000
b100 &
b100 *
b100 3
1$
#366000000
b101 &
b101 *
b101 3
0$
#367000000
b110 &
b110 *
b110 3
1$
#368000000
b111 &
b111 *
b111 3
0$
#369000000
b1000 &
b1000 *
b1000 3
1$
#370000000
b1001 &
b1001 *
b1001 3
0$
#371000000
b0 &
b0 *
b101 '
b101 +
b101 2
b0 3
1$
#372000000
b1 &
b1 *
b1 3
0$
#373000000
b10 &
b10 *
b10 3
1$
#374000000
b11 &
b11 *
b11 3
0$
#375000000
b100 &
b100 *
b100 3
1$
#376000000
b101 &
b101 *
b101 3
0$
#377000000
b110 &
b110 *
b110 3
1$
#378000000
b111 &
b111 *
b111 3
0$
#379000000
b1000 &
b1000 *
b1000 3
1$
#380000000
b1001 &
b1001 *
b1001 3
0$
#381000000
b0 &
b0 *
b110 '
b110 +
b110 2
b0 3
1$
#382000000
b1 &
b1 *
b1 3
0$
#383000000
b10 &
b10 *
b10 3
1$
#384000000
b11 &
b11 *
b11 3
0$
#385000000
b100 &
b100 *
b100 3
1$
#386000000
b101 &
b101 *
b101 3
0$
#387000000
b110 &
b110 *
b110 3
1$
#388000000
b111 &
b111 *
b111 3
0$
#389000000
b1000 &
b1000 *
b1000 3
1$
#390000000
b1001 &
b1001 *
b1001 3
0$
#391000000
b0 &
b0 *
b111 '
b111 +
b111 2
b0 3
1$
#392000000
b1 &
b1 *
b1 3
0$
#393000000
b10 &
b10 *
b10 3
1$
#394000000
b11 &
b11 *
b11 3
0$
#395000000
b100 &
b100 *
b100 3
1$
#396000000
b101 &
b101 *
b101 3
0$
#397000000
b110 &
b110 *
b110 3
1$
#398000000
b111 &
b111 *
b111 3
0$
#399000000
b1000 &
b1000 *
b1000 3
1$
#400000000
b1001 &
b1001 *
b1001 3
0$
#401000000
b0 &
b0 *
b0 '
b0 +
b0 (
b0 ,
b101 1
b0 2
b0 3
1$
#402000000
b1 &
b1 *
b1 3
0$
#403000000
b10 &
b10 *
b10 3
1$
#404000000
b11 &
b11 *
b11 3
0$
#405000000
b100 &
b100 *
b100 3
1$
#406000000
b101 &
b101 *
b101 3
0$
#407000000
b110 &
b110 *
b110 3
1$
#408000000
b111 &
b111 *
b111 3
0$
#409000000
b1000 &
b1000 *
b1000 3
1$
#410000000
b1001 &
b1001 *
b1001 3
0$
#411000000
b0 &
b0 *
b1 '
b1 +
b1 2
b0 3
1$
#412000000
b1 &
b1 *
b1 3
0$
#413000000
b10 &
b10 *
b10 3
1$
#414000000
b11 &
b11 *
b11 3
0$
#415000000
b100 &
b100 *
b100 3
1$
#416000000
b101 &
b101 *
b101 3
0$
#417000000
b110 &
b110 *
b110 3
1$
#418000000
b111 &
b111 *
b111 3
0$
#419000000
b1000 &
b1000 *
b1000 3
1$
#420000000
b1001 &
b1001 *
b1001 3
0$
#421000000
b0 &
b0 *
b10 '
b10 +
b10 2
b0 3
1$
#422000000
b1 &
b1 *
b1 3
0$
#423000000
b10 &
b10 *
b10 3
1$
#424000000
b11 &
b11 *
b11 3
0$
#425000000
b100 &
b100 *
b100 3
1$
#426000000
b101 &
b101 *
b101 3
0$
#427000000
b110 &
b110 *
b110 3
1$
#428000000
b111 &
b111 *
b111 3
0$
#429000000
b1000 &
b1000 *
b1000 3
1$
#430000000
b1001 &
b1001 *
b1001 3
0$
#431000000
b0 &
b0 *
b11 '
b11 +
b11 2
b0 3
1$
#432000000
b1 &
b1 *
b1 3
0$
#433000000
b10 &
b10 *
b10 3
1$
#434000000
b11 &
b11 *
b11 3
0$
#435000000
b100 &
b100 *
b100 3
1$
#436000000
b101 &
b101 *
b101 3
0$
#437000000
b110 &
b110 *
b110 3
1$
#438000000
b111 &
b111 *
b111 3
0$
#439000000
b1000 &
b1000 *
b1000 3
1$
#440000000
b1001 &
b1001 *
b1001 3
0$
#441000000
b0 &
b0 *
b100 '
b100 +
b100 2
b0 3
1$
#442000000
b1 &
b1 *
b1 3
0$
#443000000
b10 &
b10 *
b10 3
1$
#444000000
b11 &
b11 *
b11 3
0$
#445000000
b100 &
b100 *
b100 3
1$
#446000000
b101 &
b101 *
b101 3
0$
#447000000
b110 &
b110 *
b110 3
1$
#448000000
b111 &
b111 *
b111 3
0$
#449000000
b1000 &
b1000 *
b1000 3
1$
#450000000
b1001 &
b1001 *
b1001 3
0$
#451000000
b0 &
b0 *
b101 '
b101 +
b101 2
b0 3
1$
#452000000
b1 &
b1 *
b1 3
0$
#453000000
b10 &
b10 *
b10 3
1$
#454000000
b11 &
b11 *
b11 3
0$
#455000000
b100 &
b100 *
b100 3
1$
#456000000
b101 &
b101 *
b101 3
0$
#457000000
b110 &
b110 *
b110 3
1$
#458000000
b111 &
b111 *
b111 3
0$
#459000000
b1000 &
b1000 *
b1000 3
1$
#460000000
b1001 &
b1001 *
b1001 3
0$
#461000000
b0 &
b0 *
b110 '
b110 +
b110 2
b0 3
1$
#462000000
b1 &
b1 *
b1 3
0$
#463000000
b10 &
b10 *
b10 3
1$
#464000000
b11 &
b11 *
b11 3
0$
#465000000
b100 &
b100 *
b100 3
1$
#466000000
b101 &
b101 *
b101 3
0$
#467000000
b110 &
b110 *
b110 3
1$
#468000000
b111 &
b111 *
b111 3
0$
#469000000
b1000 &
b1000 *
b1000 3
1$
#470000000
b1001 &
b1001 *
b1001 3
0$
#471000000
b0 &
b0 *
b111 '
b111 +
b111 2
b0 3
1$
#472000000
b1 &
b1 *
b1 3
0$
#473000000
b10 &
b10 *
b10 3
1$
#474000000
b11 &
b11 *
b11 3
0$
#475000000
b100 &
b100 *
b100 3
1$
#476000000
b101 &
b101 *
b101 3
0$
#477000000
b110 &
b110 *
b110 3
1$
#478000000
b111 &
b111 *
b111 3
0$
#479000000
b1000 &
b1000 *
b1000 3
1$
#480000000
b1001 &
b1001 *
b1001 3
0$
#481000000
b110 0
b0 &
b0 *
b0 '
b0 +
0-
b110 (
b110 ,
b110 1
b0 2
b0 3
1$
#482000000
b1 &
b1 *
b1 3
0$
#483000000
b10 &
b10 *
b10 3
1$
#484000000
b11 &
b11 *
b11 3
0$
#485000000
b100 &
b100 *
b100 3
1$
#486000000
b101 &
b101 *
b101 3
0$
#487000000
b110 &
b110 *
b110 3
1$
#488000000
b111 &
b111 *
b111 3
0$
#489000000
b1000 &
b1000 *
b1000 3
1$
#490000000
b1001 &
b1001 *
b1001 3
0$
#491000000
b0 &
b0 *
b1 '
b1 +
b1 2
b0 3
1$
#492000000
b1 &
b1 *
b1 3
0$
#493000000
b10 &
b10 *
b10 3
1$
#494000000
b11 &
b11 *
b11 3
0$
#495000000
b100 &
b100 *
b100 3
1$
#496000000
b101 &
b101 *
b101 3
0$
#497000000
b110 &
b110 *
b110 3
1$
#498000000
b111 &
b111 *
b111 3
0$
#499000000
b1000 &
b1000 *
b1000 3
1$
#500000000
b1001 &
b1001 *
b1001 3
0$
#501000000
b0 &
b0 *
b10 '
b10 +
b10 2
b0 3
1$
#502000000
b1 &
b1 *
b1 3
0$
#503000000
b10 &
b10 *
b10 3
1$
#504000000
b11 &
b11 *
b11 3
0$
#505000000
b100 &
b100 *
b100 3
1$
#506000000
b101 &
b101 *
b101 3
0$
#507000000
b110 &
b110 *
b110 3
1$
#508000000
b111 &
b111 *
b111 3
0$
#509000000
b1000 &
b1000 *
b1000 3
1$
#510000000
b1001 &
b1001 *
b1001 3
0$
#511000000
b0 &
b0 *
b11 '
b11 +
b11 2
b0 3
1$
#512000000
b1 &
b1 *
b1 3
0$
#513000000
b10 &
b10 *
b10 3
1$
#514000000
b11 &
b11 *
b11 3
0$
#515000000
b100 &
b100 *
b100 3
1$
#516000000
b101 &
b101 *
b101 3
0$
#517000000
b110 &
b110 *
b110 3
1$
