colorTetris/source/t01_ai_ofm.sv
`default_nettype none 
module t01_ai_ofm (
    input logic clk, rst, mmu_done,
    input logic [17:0] mmu_result_i,
    input logic [3:0] blockX_i, 
    input logic [4:0] block_type_i, 
    output logic [3:0] blockX_o, 
    output logic [4:0] block_type_o,  
    output logic done
); 
    logic [4:0] c_block_type, n_block_type;
    logic [3:0] c_blockX, n_blockX;  
    logic [17:0] c_mmu_result, n_mmu_result; 
    logic testing; 
    assign testing = mmu_result_i > c_mmu_result; 

    assign blockX_o = c_blockX; 
    assign block_type_o = c_block_type; 
    always_ff @(posedge clk, posedge rst) begin 
        if (rst) begin 
            c_mmu_result <= 0; 
            c_block_type <= 0;
            c_blockX <= 0; 
            done <= 0; 
        end else if (mmu_done) begin 
            c_blockX <= n_blockX; 
            c_block_type <= n_block_type; 
            c_mmu_result <= n_mmu_result; 
            done <= 1'b1; 
        end else begin 
            done <= 0; 
        end
    end 

    always_comb begin 
        n_mmu_result = c_mmu_result; 
        n_blockX = c_blockX; 
        n_block_type = c_block_type; 

        if (mmu_result_i > c_mmu_result) begin 
            n_blockX = blockX_i; 
            n_block_type = block_type_i; 
            n_mmu_result = mmu_result_i; 
        end
    end
endmodule

colorTetris/testbench/t01_ai_ofm_tb.sv
`timescale 1us/1ps
module t01_ai_ofm_tb; 
    logic clk, rst;
    logic mmu_done; 
    logic [17:0] mmu_result_i; 
    logic [3:0] blockX_i; 
    logic [4:0] block_type_i; 
    logic [3:0] blockX_o; 
    logic [4:0] block_type_o; 
    logic done; 
     
   
    t01_ai_ofm ge (.clk(clk), .rst(rst), .mmu_done(mmu_done), .mmu_result_i(mmu_result_i), .blockX_i(blockX_i), .block_type_i(block_type_i), .blockX_o(blockX_o), .block_type_o(block_type_o), .done(done)); 

    task tog_rst; 
        rst = 1; #1; 
        rst = 0; 
    endtask 

    initial clk = 0; 
    always clk = #1 ~clk; 

 
    initial begin 
        $dumpfile("waves/t01_ai_ofm.vcd"); 
        $dumpvars(0, t01_ai_ofm_tb);

        blockX_i = 'd7; 
        block_type_i = 'd3; 
        mmu_done = 1'b1; 
        tog_rst(); 
            
                for (int j = 3; j <= 'd7; j++) begin 
                    for (int k = 2; k <= 'd9; k++) begin 
                        for (int i = 0; i <= 'd10; i++) begin 
                        if (i == 'd5) begin 
                            mmu_result_i = 'd0; 
                        end else begin 
                            mmu_result_i = i[17:0];
                        end  
                        block_type_i = j[4:0]; 
                        blockX_i = k[3:0]; 
                        #1; 
                    end
                end
            end

    #1 $finish; 
    end
endmodule

colorTetris/waves/t01_ai_ofm.vcd
$date
	Sat Aug  2 15:52:41 2025
$end
$version
	Icarus Verilog
$end
$timescale
	1ps
$end
$scope module t01_ai_ofm_tb $end
$var wire 1 ! done $end
$var wire 5 " block_type_o [4:0] $end
$var wire 4 # blockX_o [3:0] $end
$var reg 4 $ blockX_i [3:0] $end
$var reg 5 % block_type_i [4:0] $end
$var reg 1 & clk $end
$var reg 1 ' mmu_done $end
$var reg 18 ( mmu_result_i [17:0] $end
$var reg 1 ) rst $end
$scope module ge $end
$var wire 4 * blockX_i [3:0] $end
$var wire 4 + blockX_o [3:0] $end
$var wire 5 , block_type_i [4:0] $end
$var wire 5 - block_type_o [4:0] $end
$var wire 1 & clk $end
$var wire 1 ' mmu_done $end
$var wire 18 . mmu_result_i [17:0] $end
$var wire 1 ) rst $end
$var wire 1 / testing $end
$var reg 4 0 c_blockX [3:0] $end
$var reg 5 1 c_block_type [4:0] $end
$var reg 18 2 c_mmu_result [17:0] $end
$var reg 1 ! done $end
$var reg 4 3 n_blockX [3:0] $end
$var reg 5 4 n_block_type [4:0] $end
$var reg 18 5 n_mmu_result [17:0] $end
$upscope $end
$scope begin $ivl_for_loop0 $end
$var integer 32 6 j [31:0] $end
$scope begin $ivl_for_loop1 $end
$var integer 32 7 k [31:0] $end
$scope begin $ivl_for_loop2 $end
$var integer 32 8 i [31:0] $end
$upscope $end
$upscope $end
$upscope $end
$scope task tog_rst $end
$upscope $end
$upscope $end
$enddefinitions $end
$comment Show the parameter values. $end
$dumpall
$end
#0
$dumpvars
b0 8
b0 7
b0 6
b0 5
b0 4
b0 3
b0 2
b0 1
b0 0
x/
bx .
b0 -
b11 ,
b0 +
b111 *
1)
bx (
1'
0&
b11 %
b111 $
b0 #
b0 "
0!
$end
#1000000
1!
b10 $
b10 *
0/
b0 (
b0 .
b10 7
b11 6
0)
1&
#2000000
b1 5
b11 4
b10 3
1/
b1 (
b1 .
b1 8
0&
#3000000
b1 2
b11 "
b11 -
b11 1
b10 #
b10 +
b10 0
b11 4
b10 3
b10 5
b10 (
b10 .
b10 8
1&
#4000000
b11 5
b11 (
b11 .
b11 8
0&
#5000000
b11 2
b100 5
b100 (
b100 .
b100 8
1&
#6000000
b11 5
0/
b0 (
b0 .
b101 8
0&
#7000000
b110 5
1/
b110 (
b110 .
b110 8
1&
#8000000
b111 5
b111 (
b111 .
b111 8
0&
#9000000
b111 2
b1000 5
b1000 (
b1000 .
b1000 8
1&
#10000000
b1001 5
b1001 (
b1001 .
b1001 8
0&
#11000000
b1001 2
b1010 5
b1010 (
b1010 .
b1010 8
1&
#12000000
b1001 5
b11 $
b11 *
0/
b0 (
b0 .
b11 7
b0 8
0&
#13000000
b1 (
b1 .
b1 8
1&
#14000000
b10 (
b10 .
b10 8
0&
#15000000
b11 (
b11 .
b11 8
1&
#16000000
b100 (
b100 .
b100 8
0&
#17000000
b0 (
b0 .
b101 8
1&
#18000000
b110 (
b110 .
b110 8
0&
#19000000
b111 (
b111 .
b111 8
1&
#20000000
b1000 (
b1000 .
b1000 8
0&
#21000000
b1001 (
b1001 .
b1001 8
1&
#22000000
b1010 5
b11 3
1/
b1010 (
b1010 .
b1010 8
0&
#23000000
b1010 2
b11 #
b11 +
b11 0
b11 3
b1010 5
b100 $
b100 *
0/
b0 (
b0 .
b100 7
b0 8
1&
#24000000
b1 (
b1 .
b1 8
0&
#25000000
b10 (
b10 .
b10 8
1&
#26000000
b11 (
b11 .
b11 8
0&
#27000000
b100 (
b100 .
b100 8
1&
#28000000
b0 (
b0 .
b101 8
0&
#29000000
b110 (
b110 .
b110 8
1&
#30000000
b111 (
b111 .
b111 8
0&
#31000000
b1000 (
b1000 .
b1000 8
1&
#32000000
b1001 (
b1001 .
b1001 8
0&
#33000000
b1010 (
b1010 .
b1010 8
1&
#34000000
b101 $
b101 *
b0 (
b0 .
b101 7
b0 8
0&
#35000000
b1 (
b1 .
b1 8
1&
#36000000
b10 (
b10 .
b10 8
0&
#37000000
b11 (
b11 .
b11 8
1&
#38000000
b100 (
b100 .
b100 8
0&
#39000000
b0 (
b0 .
b101 8
1&
#40000000
b110 (
b110 .
b110 8
0&
#41000000
b111 (
b111 .
b111 8
1&
#42000000
b1000 (
b1000 .
b1000 8
0&
#43000000
b1001 (
b1001 .
b1001 8
1&
#44000000
b1010 (
b1010 .
b1010 8
0&
#45000000
b110 $
b110 *
b0 (
b0 .
b110 7
b0 8
1&
#46000000
b1 (
b1 .
b1 8
0&
#47000000
b10 (
b10 .
b10 8
1&
#48000000
b11 (
b11 .
b11 8
0&
#49000000
b100 (
b100 .
b100 8
1&
#50000000
b0 (
b0 .
b101 8
0&
#51000000
b110 (
b110 .
b110 8
1&
#52000000
b111 (
b111 .
b111 8
0&
#53000000
b1000 (
b1000 .
b1000 8
1&
#54000000
b1001 (
b1001 .
b1001 8
0&
#55000000
b1010 (
b1010 .
b1010 8
1&
#56000000
b111 $
b111 *
b0 (
b0 .
b111 7
b0 8
0&
#57000000
b1 (
b1 .
b1 8
1&
#58000000
b10 (
b10 .
b10 8
0&
#59000000
b11 (
b11 .
b11 8
1&
#60000000
b100 (
b100 .
b100 8
0&
#61000000
b0 (
b0 .
b101 8
1&
#62000000
b110 (
b110 .
b110 8
0&
#63000000
b111 (
b111 .
b111 8
1&
#64000000
b1000 (
b1000 .
b1000 8
0&
#65000000
b1001 (
b1001 .
b1001 8
1&
#66000000
b1010 (
b1010 .
b1010 8
0&
#67000000
b1000 $
b1000 *
b0 (
b0 .
b1000 7
b0 8
1&
#68000000
b1 (
b1 .
b1 8
0&
#69000000
b10 (
b10 .
b10 8
1&
#70000000
b11 (
b11 .
b11 8
0&
#71000000
b100 (
b100 .
b100 8
1&
#72000000
b0 (
b0 .
b101 8
0&
#73000000
b110 (
b110 .
b110 8
1&
#74000000
b111 (
b111 .
b111 8
0&
#75000000
b1000 (
b1000 .
b1000 8
1&
#76000000
b1001 (
b1001 .
b1001 8
0&
#77000000
b1010 (
b1010 .
b1010 8
1&
#78000000
b1001 $
b1001 *
b0 (
b0 .
b1001 7
b0 8
0&
#79000000
b1 (
b1 .
b1 8
1&
#80000000
b10 (
b10 .
b10 8
0&
#81000000
b11 (
b11 .
b11 8
1&
#82000000
b100 (
b100 .
b100 8
0&
#83000000
b0 (
b0 .
b101 8
1&
#84000000
b110 (
b110 .
b110 8
0&
#85000000
b111 (
b111 .
b111 8
1&
#86000000
b1000 (
b1000 .
b1000 8
0&
#87000000
b1001 (
b1001 .
b1001 8
1&
#88000000
b1010 (
b1010 .
b1010 8
0&
#89000000
b10 $
b10 *
b100 %
b100 ,
b0 (
b0 .
b100 6
b10 7
b0 8
1&
#90000000
b1 (
b1 .
b1 8
0&
#91000000
b10 (
b10 .
b10 8
1&
#92000000
b11 (
b11 .
b11 8
0&
#93000000
b100 (
b100 .
b100 8
1&
#94000000
b0 (
b0 .
b101 8
0&
#95000000
b110 (
b110 .
b110 8
1&
#96000000
b111 (
b111 .
b111 8
0&
#97000000
b1000 (
b1000 .
b1000 8
1&
#98000000
b1001 (
b1001 .
b1001 8
0&
#99000000
b1010 (
b1010 .
b1010 8
1&
#100000000
b11 $
b11 *
b0 (
b0 .
b11 7
b0 8
0&
#101000000
b1 (
b1 .
b1 8
1&
#102000000
b10 (
b10 .
b10 8
0&
#103000000
b11 (
b11 .
b11 8
1&
#104000000
b100 (
b100 .
b100 8
0&
#105000000
b0 (
b0 .
b101 8
1&
#106000000
b110 (
b110 .
b110 8
0&
#107000000
b111 (
b111 .
b111 8
1&
#108000000
b1000 (
b1000 .
b1000 8
0&
#109000000
b1001 (
b1001 .
b1001 8
1&
#110000000
b1010 (
b1010 .
b1010 8
0&
#111000000
b100 $
b100 *
b0 (
b0 .
b100 7
b0 8
1&
#112000000
b1 (
b1 .
b1 8
0&
#113000000
b10 (
b10 .
b10 8
1&
#114000000
b11 (
b11 .
b11 8
0&
#115000000
b100 (
b100 .
b100 8
1&
#116000000
b0 (
b0 .
b101 8
0&
#117000000
b110 (
b110 .
b110 8
1&
#118000000
b111 (
b111 .
b111 8
0&
#119000000
b1000 (
b1000 .
b1000 8
1&
#120000000
b1001 (
b1001 .
b1001 8
0&
#121000000
b1010 (
b1010 .
b1010 8
1&
#122000000
b101 $
b101 *
b0 (
b0 .
b101 7
b0 8
0&
#123000000
b1 (
b1 .
b1 8
1&
#124000000
b10 (
b10 .
b10 8
0&
#125000000
b11 (
b11 .
b11 8
1&
#126000000
b100 (
b100 .
b100 8
0&
#127000000
b0 (
b0 .
b101 8
1&
#128000000
b110 (
b110 .
b110 8
0&
#129000000
b111 (
b111 .
b111 8
1&
#130000000
b1000 (
b1000 .
b1000 8
0&
#131000000
b1001 (
b1001 .
b1001 8
1&
#132000000
b1010 (
b1010 .
b1010 8
0&
#133000000
b110 $
b110 *
b0 (
b0 .
b110 7
b0 8
1&
#134000000
b1 (
b1 .
b1 8
0&
#135000000
b10 (
b10 .
b10 8
1&
#136000000
b11 (
b11 .
b11 8
0&
#137000000
b100 (
b100 .
b100 8
1&
#138000000
b0 (
b0 .
b101 8
0&
#139000000
b110 (
b110 .
b110 8
1&
#140000000
b111 (
b111 .
b111 8
0&
#141000000
b1000 (
b1000 .
b1000 8
1&
#142000000
b1001 (
b1001 .
b1001 8
0&
#143000000
b1010 (
b1010 .
b1010 8
1&
#144000000
b111 $
b111 *
b0 (
b0 .
b111 7
b0 8
0&
#145000000
b1 (
b1 .
b1 8
1&
#146000000
b10 (
b10 .
b10 8
0&
#147000000
b11 (
b11 .
b11 8
1&
#148000000
b100 (
b100 .
b100 8
0&
#149000000
b0 (
b0 .
b101 8
1&
#150000000
b110 (
b110 .
b110 8
0&
#151000000
b111 (
b111 .
b111 8
1&
#152000000
b1000 (
b1000 .
b1000 8
0&
#153000000
b1001 (
b1001 .
b1001 8
1&
#154000000
b1010 (
b1010 .
b1010 8
0&
#155000000
b1000 $
b1000 *
b0 (
b0 .
b1000 7
b0 8
1&
#156000000
b1 (
b1 .
b1 8
0&
#157000000
b10 (
b10 .
b10 8
1&
#158000000
b11 (
b11 .
b11 8
0&
#159000000
b100 (
b100 .
b100 8
1&
#160000000
b0 (
b0 .
b101 8
0&
#161000000
b110 (
b110 .
b110 8
1&
#162000000
b111 (
b111 .
b111 8
0&
#163000000
b1000 (
b1000 .
b1000 8
1&
#164000000
b1001 (
b1001 .
b1001 8
0&
#165000000
b1010 (
b1010 .
b1010 8
1&
#166000000
b1001 $
b1001 *
b0 (
b0 .
b1001 7
b0 8
0&
#167000000
b1 (
b1 .
b1 8
1&
#168000000
b10 (
b10 .
b10 8
0&
#169000000
b11 (
b11 .
b11 8
1&
#170000000
b100 (
b100 .
b100 8
0&
#171000000
b0 (
b0 .
b101 8
1&
#172000000
b110 (
b110 .
b110 8
0&
#173000000
b111 (
b111 .
b111 8
1&
#174000000
b1000 (
b1000 .
b1000 8
0&
#175000000
b1001 (
b1001 .
b1001 8
1&
#176000000
b1010 (
b1010 .
b1010 8
0&
#177000000
b10 $
b10 *
b101 %
b101 ,
b0 (
b0 .
b101 6
b10 7
b0 8
1&
#178000000
b1 (
b1 .
b1 8
0&
#179000000
b10 (
b10 .
b10 8
1&
#180000000
b11 (
b11 .
b11 8
0&
#181000000
b100 (
b100 .
b100 8
1&
#182000000
b0 (
b0 .
b101 8
0&
#183000000
b110 (
b110 .
b110 8
1&
#184000000
b111 (
b111 .
b111 8
0&
#185000000
b1000 (
b1000 .
b1000 8
1&
#186000000
b1001 (
b1001 .
b1001 8
0&
#187000000
b1010 (
b1010 .
b1010 8
1&
#188000000
b11 $
b11 *
b0 (
b0 .
b11 7
b0 8
0&
#189000000
b1 (
b1 .
b1 8
1&
#190000000
b10 (
b10 .
b10 8
0&
#191000000
b11 (
b11 .
b11 8
1&
#192000000
b100 (
b100 .
b100 8
0&
#193000000
b0 (
b0 .
b101 8
1&
#194000000
b110 (
b110 .
b110 8
0&
#195000000
b111 (
b111 .
b111 8
1&
#196000000
b1000 (
b1000 .
b1000 8
0&
#197000000
b1001 (
b1001 .
b1001 8
1&
#198000000
b1010 (
b1010 .
b1010 8
0&
#199000000
b100 $
b100 *
b0 (
b0 .
b100 7
b0 8
1&
#200000000
b1 (
b1 .
b1 8
0&
#201000000
b10 (
b10 .
b10 8
1&
#202000000
b11 (
b11 .
b11 8
0&
#203000000
b100 (
b100 .
b100 8
1&
#204000000
b0 (
b0 .
b101 8
0&
#205000000
b110 (
b110 .
b110 8
1&
#206000000
b111 (
b111 .
b111 8
0&
#207000000
b1000 (
b1000 .
b1000 8
1&
#208000000
b1001 (
b1001 .
b1001 8
0&
#209000000
b1010 (
b1010 .
b1010 8
1&
#210000000
b101 $
b101 *
b0 (
b0 .
b101 7
b0 8
0&
#211000000
b1 (
b1 .
b1 8
1&
#212000000
b10 (
b10 .
b10 8
0&
#213000000
b11 (
b11 .
b11 8
1&
#214000000
b100 (
b100 .
b100 8
0&
#215000000
b0 (
b0 .
b101 8
1&
#216000000
b110 (
b110 .
b110 8
0&
#217000000
b111 (
b111 .
b111 8
1&
#218000000
b1000 (
b1000 .
b1000 8
0&
#219000000
b1001 (
b1001 .
b1001 8
1&
#220000000
b1010 (
b1010 .
b1010 8
0&
#221000000
b110 $
b110 *
b0 (
b0 .
b110 7
b0 8
1&
#222000000
b1 (
b1 .
b1 8
0&
#223000000
b10 (
b10 .
b10 8
1&
#224000000
b11 (
b11 .
b11 8
0&
#225000000
b100 (
b100 .
b100 8
1&
#226000000
b0 (
b0 .
b101 8
0&
#227000000
b110 (
b110 .
b110 8
1&
#228000000
b111 (
b111 .
b111 8
0&
#229000000
b1000 (
b1000 .
b1000 8
1&
#230000000
b1001 (
b1001 .
b1001 8
0&
#231000000
b1010 (
b1010 .
b1010 8
1&
#232000000
b111 $
b111 *
b0 (
b0 .
b111 7
b0 8
0&
#233000000
b1 (
b1 .
b1 8
1&
#234000000
b10 (
b10 .
b10 8
0&
#235000000
b11 (
b11 .
b11 8
1&
#236000000
b100 (
b100 .
b100 8
0&
#237000000
b0 (
b0 .
b101 8
1&
#238000000
b110 (
b110 .
b110 8
0&
#239000000
b111 (
b111 .
b111 8
1&
#240000000
b1000 (
b1000 .
b1000 8
0&
#241000000
b1001 (
b1001 .
b1001 8
1&
#242000000
b1010 (
b1010 .
b1010 8
0&
#243000000
b1000 $
b1000 *
b0 (
b0 .
b1000 7
b0 8
1&
#244000000
b1 (
b1 .
b1 8
0&
#245000000
b10 (
b10 .
b10 8
1&
#246000000
b11 (
b11 .
b11 8
0&
#247000000
b100 (
b100 .
b100 8
1&
#248000000
b0 (
b0 .
b101 8
0&
#249000000
b110 (
b110 .
b110 8
1&
#250000000
b111 (
b111 .
b111 8
0&
#251000000
b1000 (
b1000 .
b1000 8
1&
#252000000
b1001 (
b1001 .
b1001 8
0&
#253000000
b1010 (
b1010 .
b1010 8
1&
#254000000
b1001 $
b1001 *
b0 (
b0 .
b1001 7
b0 8
0&
#255000000
b1 (
b1 .
b1 8
1&
#256000000
b10 (
b10 .
b10 8
0&
#257000000
b11 (
b11 .
b11 8
1&
#258000000
b100 (
b100 .
b100 8
0&
#259000000
b0 (
b0 .
b101 8
1&
#260000000
b110 (
b110 .
b110 8
0&
#261000000
b111 (
b111 .
b111 8
1&
#262000000
b1000 (
b1000 .
b1000 8
0&
#263000000
b1001 (
b1001 .
b1001 8
1&
#264000000
b1010 (
b1010 .
b1010 8
0&
#265000000
b10 $
b10 *
b110 %
b110 ,
b0 (
b0 .
b110 6
b10 7
b0 8
1&
#266000000
b1 (
b1 .
b1 8
0&
#267000000
b10 (
b10 .
b10 8
1&
#268000000
b11 (
b11 .
b11 8
0&
#269000000
b100 (
b100 .
b100 8
1&
#270000000
b0 (
b0 .
b101 8
0&
#271000000
b110 (
b110 .
b110 8
1&
#272000000
b111 (
b111 .
b111 8
0&
#273000000
b1000 (
b1000 .
b1000 8
1&
#274000000
b1001 (
b1001 .
b1001 8
0&
#275000000
b1010 (
b1010 .
b1010 8
1&
#276000000
b11 $
b11 *
b0 (
b0 .
b11 7
b0 8
0&
#277000000
b1 (
b1 .
b1 8
1&
#278000000
b10 (
b10 .
b10 8
0&
#279000000
b11 (
b11 .
b11 8
1&
#280000000
b100 (
b100 .
b100 8
0&
#281000000
b0 (
b0 .
b101 8
1&
#282000000
b110 (
b110 .
b110 8
0&
#283000000
b111 (
b111 .
b111 8
1&
#284000000
b1000 (
b1000 .
b1000 8
0&
#285000000
b1001 (
b1001 .
b1001 8
1&
#286000000
b1010 (
b1010 .
b1010 8
0&
#287000000
b100 $
b100 *
b0 (
b0 .
b100 7
b0 8
1&
#288000000
b1 (
b1 .
b1 8
0&
#289000000
b10 (
b10 .
b10 8
1&
#290000000
b11 (
b11 .
b11 8
0&
#291000000
b100 (
b100 .
b100 8
1&
#292000000
b0 (
b0 .
b101 8
0&
#293000000
b110 (
b110 .
b110 8
1&
#294000000
b111 (
b111 .
b111 8
0&
#295000000
b1000 (
b1000 .
b1000 8
1&
#296000000
b1001 (
b1001 .
b1001 8
0&
#297000000
b1010 (
b1010 .
b1010 8
1&
#298000000
b101 $
b101 *
b0 (
b0 .
b101 7
b0 8
0&
#299000000
b1 (
b1 .
b1 8
1&
#300000000
b10 (
b10 .
b10 8
0&
#301000000
b11 (
b11 .
b11 8
1&
#302000000
b100 (
b100 .
b100 8
0&
#303000000
b0 (
b0 .
b101 8
1&
#304000000
b110 (
b110 .
b110 8
0&
#305000000
b111 (
b111 .
b111 8
1&
#306000000
b1000 (
b1000 .
b1000 8
0&
#307000000
b1001 (
b1001 .
b1001 8
1&
#308000000
b1010 (
b1010 .
b1010 8
0&
#309000000
b110 $
b110 *
b0 (
b0 .
b110 7
b0 8
1&
#310000000
b1 (
b1 .
b1 8
0&
#311000000
b10 (
b10 .
b10 8
1&
#312000000
b11 (
b11 .
b11 8
0&
#313000000
b100 (
b100 .
b100 8
1&
#314000000
b0 (
b0 .
b101 8
0&
#315000000
b110 (
b110 .
b110 8
1&
#316000000
b111 (
b111 .
b111 8
0&
#317000000
b1000 (
b1000 .
b1000 8
1&
#318000000
b1001 (
b1001 .
b1001 8
0&
#319000000
b1010 (
b1010 .
b1010 8
1&
#320000000
b111 $
b111 *
b0 (
b0 .
b111 7
b0 8
0&
#321000000
b1 (
b1 .
b1 8
1&
#322000000
b10 (
b10 .
b10 8
0&
#323000000
b11 (
b11 .
b11 8
1&
#324000000
b100 (
b100 .
b100 8
0&
#325000000
b0 (
b0 .
b101 8
1&
#326000000
b110 (
b110 .
b110 8
0&
#327000000
b111 (
b111 .
b111 8
1&
#328000000
b1000 (
b1000 .
b1000 8
0&
#329000000
b1001 (
b1001 .
b1001 8
1&
#330000000
b1010 (
b1010 .
b1010 8
0&
#331000000
b1000 $
b1000 *
b0 (
b0 .
b1000 7
b0 8
1&
#332000000
b1 (
b1 .
b1 8
0&
#333000000
b10 (
b10 .
b10 8
1&
#334000000
b11 (
b11 .
b11 8
0&
#335000000
b100 (
b100 .
b100 8
1&
#336000000
b0 (
b0 .
b101 8
0&
#337000000
b110 (
b110 .
b110 8
1&
#338000000
b111 (
b111 .
b111 8
0&
#339000000
b1000 (
b1000 .
b1000 8
1&
#340000000
b1001 (
b1001 .
b1001 8
0&
#341000000
b1010 (
b1010 .
b1010 8
1&
#342000000
b1001 $
b1001 *
b0 (
b0 .
b1001 7
b0 8
0&
#343000000
b1 (
b1 .
b1 8
1&
#344000000
b10 (
b10 .
b10 8
0&
#345000000
b11 (
b11 .
b11 8
1&
#346000000
b100 (
b100 .
b100 8
0&
#347000000
b0 (
b0 .
b101 8
1&
#348000000
b110 (
b110 .
b110 8
0&
#349000000
b111 (
b111 .
b111 8
1&
#350000000
b1000 (
b1000 .
b1000 8
0&
#351000000
b1001 (
b1001 .
b1001 8
1&
#352000000
b1010 (
b1010 .
b1010 8
0&
#353000000
b10 $
b10 *
b111 %
b111 ,
b0 (
b0 .
b111 6
b10 7
b0 8
1&
#354000000
b1 (
b1 .
b1 8
0&
#355000000
b10 (
b10 .
b10 8
1&
#356000000
b11 (
b11 .
b11 8
0&
#357000000
b100 (
b100 .
b100 8
1&
#358000000
b0 (
b0 .
b101 8
0&
#359000000
b110 (
b110 .
b110 8
1&
#360000000
b111 (
b111 .
b111 8
0&
#361000000
b1000 (
b1000 .
b1000 8
1&
#362000000
b1001 (
b1001 .
b1001 8
0&
#363000000
b1010 (
b1010 .
b1010 8
1&
#364000000
b11 $
b11 *
b0 (
b0 .
b11 7
b0 8
0&
#365000000
b1 (
b1 .
b1 8
1&
#366000000
b10 (
b10 .
b10 8
0&
#367000000
b11 (
b11 .
b11 8
1&
#368000000
b100 (
b100 .
b100 8
0&
#369000000
b0 (
b0 .
b101 8
1&
#370000000
b110 (
b110 .
b110 8
0&
#371000000
b111 (
b111 .
b111 8
1&
#372000000
b1000 (
b1000 .
b1000 8
0&
#373000000
b1001 (
b1001 .
b1001 8
1&
#374000000
b1010 (
b1010 .
b1010 8
0&
#375000000
b100 $
b100 *
b0 (
b0 .
b100 7
b0 8
1&
#376000000
b1 (
b1 .
b1 8
0&
#377000000
b10 (
b10 .
b10 8
1&
#378000000
b11 (
b11 .
b11 8
0&
#379000000
b100 (
b100 .
b100 8
1&
#380000000
b0 (
b0 .
b101 8
0&
#381000000
b110 (
b110 .
b110 8
1&
#382000000
b111 (
b111 .
b111 8
0&
#383000000
b1000 (
b1000 .
b1000 8
1&
#384000000
b1001 (
b1001 .
b1001 8
0&
#385000000
b1010 (
b1010 .
b1010 8
1&
#386000000
b101 $
b101 *
b0 (
b0 .
b101 7
b0 8
0&
#387000000
b1 (
b1 .
b1 8
1&
#388000000
b10 (
b10 .
b10 8
0&
#389000000
b11 (
b11 .
b11 8
1&
#390000000
b100 (
b100 .
b100 8
0&
#391000000
b0 (
b0 .
b101 8
1&
#392000000
b110 (
b110 .
b110 8
0&
#393000000
b111 (
b111 .
b111 8
1&
#394000000
b1000 (
b1000 .
b1000 8
0&
#395000000
b1001 (
b1001 .
b1001 8
1&
#396000000
b1010 (
b1010 .
b1010 8
0&
#397000000
b110 $
b110 *
b0 (
b0 .
b110 7
b0 8
1&
#398000000
b1 (
b1 .
b1 8
0&
#399000000
b10 (
b10 .
b10 8
1&
#400000000
b11 (
b11 .
b11 8
0&
#401000000
b100 (
b100 .
b100 8
1&
#402000000
b0 (
b0 .
b101 8
0&
#403000000
b110 (
b110 .
b110 8
1&
#404000000
b111 (
b111 .
b111 8
0&
#405000000
b1000 (
b1000 .
b1000 8
1&
#406000000
b1001 (
b1001 .
b1001 8
0&
#407000000
b1010 (
b1010 .
b1010 8
1&
#408000000
b111 $
b111 *
b0 (
b0 .
b111 7
b0 8
0&
#409000000
b1 (
b1 .
b1 8
1&
#410000000
b10 (
b10 .
b10 8
0&
#411000000
b11 (
b11 .
b11 8
1&
#412000000
b100 (
b100 .
b100 8
0&
#413000000
b0 (
b0 .
b101 8
1&
#414000000
b110 (
b110 .
b110 8
0&
#415000000
b111 (
b111 .
b111 8
1&
#416000000
b1000 (
b1000 .
b1000 8
0&
#417000000
b1001 (
b1001 .
b1001 8
1&
#418000000
b1010 (
b1010 .
b1010 8
0&
#419000000
b1000 $
b1000 *
b0 (
b0 .
b1000 7
b0 8
1&
#420000000
b1 (
b1 .
b1 8
0&
#421000000
b10 (
b10 .
b10 8
1&
#422000000
b11 (
b11 .
b11 8
0&
#423000000
b100 (
b100 .
b100 8
1&
#424000000
b0 (
b0 .
b101 8
0&
#425000000
b110 (
b110 .
b110 8
1&
#426000000
b111 (
b111 .
b111 8
0&
#427000000
b1000 (
b1000 .
b1000 8
1&
#428000000
b1001 (
b1001 .
b1001 8
0&
#429000000
b1010 (
b1010 .
b1010 8
1&
#430000000
b1001 $
b1001 *
b0 (
b0 .
b1001 7
b0 8
0&
#431000000
b1 (
b1 .
b1 8
1&
#432000000
b10 (
b10 .
b10 8
0&
#433000000
b11 (
b11 .
b11 8
1&
#434000000
b100 (
b100 .
b100 8
0&
#435000000
b0 (
b0 .
b101 8
1&
#436000000
b110 (
b110 .
b110 8
0&
#437000000
b111 (
b111 .
b111 8
1&
#438000000
b1000 (
b1000 .
b1000 8
0&
#439000000
b1001 (
b1001 .
b1001 8
1&
#440000000
b1010 (
b1010 .
b1010 8
0&
#441000000
b1000 6
b1010 7
b1011 8
1&
