colorTetris/source/t01_ai_game_engine.sv
`default_nettype none
module t01_ai_game_engine (
    input logic clk, rst, 

    // tetris fsm 
    input logic [3:0] gamestate, 
    input logic collision_left, 
    output logic ai_left, ai_rotation, 

    // feature extraction 
    input logic extract_ready, // extraction done 
    output logic extract_start, 

    // inputs from ofm to stream back to tetris: mamnhattan distance + block type 
    input logic [4:0] current_block_type 

);  

    logic [19:0][9:0] last_stored_array; 
    logic ai_new_spawn; 
    logic [4:0] base_block_type; 
    logic left_en, rot_en, first_move_buffer; // determine if the ai needs to move in the next state  

    always_ff @(posedge clk, posedge rst) begin 
        if (rst) begin 
            last_stored_array <= 0; 
            extract_start <= 0; 
            ai_left <= 0; 
            ai_rotation <= 0;  
            left_en <= 1; 
            rot_en <= 1; 
            first_move_buffer <= 0; // get through the first iteratio first 
            ai_new_spawn <= 0; 
            base_block_type <= 0; 
        end else begin
            // 
            if (gamestate == 'd1) begin // spawn
                rot_en <= 1; 
                left_en <= 1;  
                first_move_buffer <= 0; 
                base_block_type <= current_block_type; 
            end else if (gamestate == 'd2) begin // falling state 
                // only make one move at a time 
                if (first_move_buffer) begin 
                    if (left_en) begin 
                        ai_left <= 1; 
                    end else if (rot_en) begin 
                        ai_rotation <= 1; 
                    end 
                end 
            end else if (gamestate == 'd10) begin // ai state 
                // set the pulse back for synkey 
                ai_left <= 0; 
                ai_rotation <= 0; 
                
                // feature extraction 
                extract_start <= 1'b1; 
                if (first_move_buffer) begin // not the first iteration 
                    if (extract_ready) begin 
                        if (collision_left && current_block_type == base_block_type) begin 
                            ai_new_spawn <= 1; 
                        end 
                    end
                end else begin 
                    first_move_buffer <= 1; // go to the AI state -> means the first STUCK happened 
                end
            end 
        end 
    end
endmodule

colorTetris/testbench/t01_ai_game_engine_tb.sv
`timescale 1us/1ps
module t01_ai_game_engine_tb; 
    logic clk, rst;
    logic [3:0] gamestate;
    logic extract_ready;
    logic extract_start;
    logic [4:0] current_block_type; 
    logic collision_left, ai_left, ai_rotation; 

   
    t01_ai_game_engine ge (.clk(clk), .rst(rst), .collision_left(collision_left), .ai_left(ai_left), .ai_rotation(ai_rotation), .gamestate(gamestate), .extract_ready(extract_ready), .extract_start(extract_start), .current_block_type(current_block_type)); 

    task tog_rst; 
        rst = 1; #1; 
        rst = 0; 
    endtask 

    initial clk = 0; 
    always clk = #1 ~clk; 

 
    initial begin 
        $dumpfile("waves/t01_ai_game_engine.vcd"); 
        $dumpvars(0, t01_ai_game_engine_tb);
        current_block_type = 'd3; 
        tog_rst(); 
        for (int m = 0; m <= 1; m++) begin 
        for (int i = 0; i <= 'd10; i++) begin 
            for (int j = 0; j <= 1; j++) begin 
                for (int k = 0; k <= 1; k ++) begin 
                    gamestate = i[3:0]; 
                    extract_ready = j[0]; 
                    collision_left = k[0]; 
                    #1; 
                end 
            end
        end
        end 

    #1 $finish; 
    end
endmodule

colorTetris/waves/t01_ai_game_engine.vcd
$date
	Fri Aug  1 21:17:26 2025
$end
$version
	Icarus Verilog
$end
$timescale
	1ps
$end
$scope module t01_ai_game_engine_tb $end
$var wire 1 ! extract_start $end
$var wire 1 " ai_rotation $end
$var wire 1 # ai_left $end
$var reg 1 $ clk $end
$var reg 1 % collision_left $end
$var reg 5 & current_block_type [4:0] $end
$var reg 1 ' extract_ready $end
$var reg 4 ( gamestate [3:0] $end
$var reg 1 ) rst $end
$scope module ge $end
$var wire 1 $ clk $end
$var wire 1 % collision_left $end
$var wire 5 * current_block_type [4:0] $end
$var wire 1 ' extract_ready $end
$var wire 4 + gamestate [3:0] $end
$var wire 1 ) rst $end
$var reg 1 # ai_left $end
$var reg 1 , ai_new_spawn $end
$var reg 1 " ai_rotation $end
$var reg 5 - base_block_type [4:0] $end
$var reg 1 ! extract_start $end
$var reg 1 . first_move_buffer $end
$var reg 200 / last_stored_array [199:0] $end
$var reg 1 0 left_en $end
$var reg 1 1 rot_en $end
$upscope $end
$scope begin $ivl_for_loop0 $end
$var integer 32 2 m [31:0] $end
$scope begin $ivl_for_loop1 $end
$var integer 32 3 i [31:0] $end
$scope begin $ivl_for_loop2 $end
$var integer 32 4 j [31:0] $end
$scope begin $ivl_for_loop3 $end
$var integer 32 5 k [31:0] $end
$upscope $end
$upscope $end
$upscope $end
$upscope $end
$scope task tog_rst $end
$upscope $end
$upscope $end
$enddefinitions $end
$comment Show the parameter values. $end
$dumpall
$end
#0
$dumpvars
b0 5
b0 4
b0 3
b0 2
11
10
b0 /
0.
b0 -
0,
bx +
b11 *
1)
bx (
x'
b11 &
x%
0$
0#
0"
0!
$end
#1000000
0%
0'
b0 (
b0 +
0)
1$
#2000000
1%
b1 5
0$
#3000000
0%
1'
b1 4
b0 5
1$
#4000000
1%
b1 5
0$
#5000000
b11 -
0%
0'
b1 (
b1 +
b1 3
b0 4
b0 5
1$
#6000000
1%
b1 5
0$
#7000000
0%
1'
b1 4
b0 5
1$
#8000000
1%
b1 5
0$
#9000000
0%
0'
b10 (
b10 +
b10 3
b0 4
b0 5
1$
#10000000
1%
b1 5
0$
#11000000
0%
1'
b1 4
b0 5
1$
#12000000
1%
b1 5
0$
#13000000
0%
0'
b11 (
b11 +
b11 3
b0 4
b0 5
1$
#14000000
1%
b1 5
0$
#15000000
0%
1'
b1 4
b0 5
1$
#16000000
1%
b1 5
0$
#17000000
0%
0'
b100 (
b100 +
b100 3
b0 4
b0 5
1$
#18000000
1%
b1 5
0$
#19000000
0%
1'
b1 4
b0 5
1$
#20000000
1%
b1 5
0$
#21000000
0%
0'
b101 (
b101 +
b101 3
b0 4
b0 5
1$
#22000000
1%
b1 5
0$
#23000000
0%
1'
b1 4
b0 5
1$
#24000000
1%
b1 5
0$
#25000000
0%
0'
b110 (
b110 +
b110 3
b0 4
b0 5
1$
#26000000
1%
b1 5
0$
#27000000
0%
1'
b1 4
b0 5
1$
#28000000
1%
b1 5
0$
#29000000
0%
0'
b111 (
b111 +
b111 3
b0 4
b0 5
1$
#30000000
1%
b1 5
0$
#31000000
0%
1'
b1 4
b0 5
1$
#32000000
1%
b1 5
0$
#33000000
0%
0'
b1000 (
b1000 +
b1000 3
b0 4
b0 5
1$
#34000000
1%
b1 5
0$
#35000000
0%
1'
b1 4
b0 5
1$
#36000000
1%
b1 5
0$
#37000000
0%
0'
b1001 (
b1001 +
b1001 3
b0 4
b0 5
1$
#38000000
1%
b1 5
0$
#39000000
0%
1'
b1 4
b0 5
1$
#40000000
1%
b1 5
0$
#41000000
1.
1!
0%
0'
b1010 (
b1010 +
b1010 3
b0 4
b0 5
1$
#42000000
1%
b1 5
0$
#43000000
0%
1'
b1 4
b0 5
1$
#44000000
1%
b1 5
0$
#45000000
0%
0'
b0 (
b0 +
b1 2
b0 3
b0 4
b0 5
1$
#46000000
1%
b1 5
0$
#47000000
0%
1'
b1 4
b0 5
1$
#48000000
1%
b1 5
0$
#49000000
0.
0%
0'
b1 (
b1 +
b1 3
b0 4
b0 5
1$
#50000000
1%
b1 5
0$
#51000000
0%
1'
b1 4
b0 5
1$
#52000000
1%
b1 5
0$
#53000000
0%
0'
b10 (
b10 +
b10 3
b0 4
b0 5
1$
#54000000
1%
b1 5
0$
#55000000
0%
1'
b1 4
b0 5
1$
#56000000
1%
b1 5
0$
#57000000
0%
0'
b11 (
b11 +
b11 3
b0 4
b0 5
1$
#58000000
1%
b1 5
0$
#59000000
0%
1'
b1 4
b0 5
1$
#60000000
1%
b1 5
0$
#61000000
0%
0'
b100 (
b100 +
b100 3
b0 4
b0 5
1$
#62000000
1%
b1 5
0$
#63000000
0%
1'
b1 4
b0 5
1$
#64000000
1%
b1 5
0$
#65000000
0%
0'
b101 (
b101 +
b101 3
b0 4
b0 5
1$
#66000000
1%
b1 5
0$
#67000000
0%
1'
b1 4
b0 5
1$
#68000000
1%
b1 5
0$
#69000000
0%
0'
b110 (
b110 +
b110 3
b0 4
b0 5
1$
#70000000
1%
b1 5
0$
#71000000
0%
1'
b1 4
b0 5
1$
#72000000
1%
b1 5
0$
#73000000
0%
0'
b111 (
b111 +
b111 3
b0 4
b0 5
1$
#74000000
1%
b1 5
0$
#75000000
0%
1'
b1 4
b0 5
1$
#76000000
1%
b1 5
0$
#77000000
0%
0'
b1000 (
b1000 +
b1000 3
b0 4
b0 5
1$
#78000000
1%
b1 5
0$
#79000000
0%
1'
b1 4
b0 5
1$
#80000000
1%
b1 5
0$
#81000000
0%
0'
b1001 (
b1001 +
b1001 3
b0 4
b0 5
1$
#82000000
1%
b1 5
0$
#83000000
0%
1'
b1 4
b0 5
1$
#84000000
1%
b1 5
0$
#85000000
1.
0%
0'
b1010 (
b1010 +
b1010 3
b0 4
b0 5
1$
#86000000
1%
b1 5
0$
#87000000
0%
1'
b1 4
b0 5
1$
#88000000
1%
b1 5
0$
#89000000
1,
b10 2
b1011 3
b10 4
b10 5
1$
