source/ai_cu_id.sv
`default_nettype none
/////////////////////////////////////////////////////////////////
// HEADER 
//
// Module : ai_cu_id
// Description : Instruction Decoder of the Control Unit inside 
//               the AI Accelerator 
// 
//             layer_type code	 
//             4’b0000	Convolutional layer
//             4’b0001	Pooling layer (Max/Average)
//             4’b0010	Activation only (ReLU)
//             4’b0011	Fully-Connected (GEMV)
//             4’b0100	Bypass / Identity
//         pending: 
//             4’b0101	Tetris Grid Preprocessing 
//             4’b0110	Move Generation
//             4’b0111  Sfotmax/ArgMax (final layer)	
//             4’b1000  Grid Feature Extraction 	
//             
//
/////////////////////////////////////////////////////////////////
module ai_cu_id #(
  parameter int K_WIDTH = 4, // kernel_size bits 
  parameter int S_WIDTH = 4, // stride bits 
  parameter int TYPE_WIDTH = 4, // layer_type bits 
  parameter int INST_WIDTH = K_WIDTH + S_WIDTH + TYPE_WIDTH + 2// width of the instruction word 
) (
  input logic clk, rst, 
  input logic start_layer, // strobe from host / FSM to load new inst 
  input logic [INST_WIDTH-1:0] inst_word_in, // 32-bit layer descripter 

  output logic start_decoded, // one-cycle pulse - params latched 
  output logic [K_WIDTH-1:0] kernel_size, 
  output logic [S_WIDTH-1:0] stride, 
  output logic relu_en, 
  output logic pool_en, 
  output logic [TYPE_WIDTH-1:0] layer_type 
);

  // internal registers 
  logic [INST_WIDTH-1:0] inst_reg; 
  logic start_layer_d; 

  always_ff @(posedge clk, posedge rst) begin 
    if (rst) begin 
      // instruction register: latch the incoming inst_word on start_layer 
      inst_reg <= 0; 

      // start_decoded pulse generation: produce a one-cycle pulse when inst_reg is just loaded 
      start_layer_d <= 1'b0; 
      start_decoded <= 1'b0; 
    end else begin 
      inst_reg <= inst_word_in; 

      start_decoded <= start_layer & ~start_layer_d; 
      start_layer_d <= start_layer; 
    end 
  end

  // field extraction - bit-sliced 
  assign layer_type = inst_reg[INST_WIDTH-1-:TYPE_WIDTH]; 
  assign kernel_size = inst_reg[INST_WIDTH-TYPE_WIDTH-1-:K_WIDTH]; // kernel size bits: [23:20]
  assign stride = inst_reg[INST_WIDTH-TYPE_WIDTH-K_WIDTH-1-:S_WIDTH]; // stride bits: [19:16]
  assign relu_en = inst_reg[INST_WIDTH-TYPE_WIDTH-K_WIDTH-S_WIDTH-1]; 
  assign pool_en = inst_reg[INST_WIDTH-TYPE_WIDTH-K_WIDTH-S_WIDTH-2]; 

endmodule

testbench/ai_cu_id_tb.sv
`timescale 1ms/10ps
module ai_cu_id_tb #(
parameter int K_WIDTH = 4, // kernel_size bits 
  parameter int S_WIDTH = 4, // stride bits 
  parameter int TYPE_WIDTH = 4, // layer_type bits 
  parameter int INST_WIDTH = K_WIDTH + S_WIDTH + TYPE_WIDTH + 2// width of the instruction word 
);

    logic clk, rst;
    logic start_layer;// strobe from host / FSM to load new inst 
    logic [INST_WIDTH-1:0] inst_word_in;// 32-bit layer descripter 

    logic start_decoded;// one-cycle pulse - params latched 
    logic [K_WIDTH-1:0] kernel_size;
    logic [S_WIDTH-1:0] stride;
    logic relu_en;
    logic pool_en;
    logic [TYPE_WIDTH-1:0] layer_type; 

    ai_cu_id instruction_decoder (.clk(clk), .rst(rst), .start_layer(start_layer), .start_decoded(start_decoded), .inst_word_in(inst_word_in), .kernel_size(kernel_size), .stride(stride), .relu_en(relu_en), .pool_en(pool_en), .layer_type(layer_type)); 
    
    task tog_rst();
      rst = 1; #1; 
      rst = 0; 
    endtask 

    task tog_start();
      start_layer = 1; #1; 
      start_layer = 0; #1; 
    endtask 

    initial clk = 0; 
    always clk = #1 ~clk; 

    initial begin 
      $dumpfile("waves/ai_cu_id.vcd"); 
      $dumpvars(0, ai_cu_id_tb); 

      inst_word_in = 0; 
      tog_rst(); 

      for (int i = 0; i <= 2**INST_WIDTH; i++) begin 
        inst_word_in = i[13:0]; 
        tog_start(); 
      end

      #1 $finish; 
    end
endmodule

waves/ai_cu_id.vcd
$date
	Wed Jul 23 11:16:53 2025
$end
$version
	Icarus Verilog
$end
$timescale
	10ps
$end
$scope module ai_cu_id_tb $end
$var wire 4 ! stride [3:0] $end
$var wire 1 " start_decoded $end
$var wire 1 # relu_en $end
$var wire 1 $ pool_en $end
$var wire 4 % layer_type [3:0] $end
$var wire 4 & kernel_size [3:0] $end
$var parameter 32 ' INST_WIDTH $end
$var parameter 32 ( K_WIDTH $end
$var parameter 32 ) S_WIDTH $end
$var parameter 32 * TYPE_WIDTH $end
$var reg 1 + clk $end
$var reg 14 , inst_word_in [13:0] $end
$var reg 1 - rst $end
$var reg 1 . start_layer $end
$scope module instruction_decoder $end
$var wire 1 + clk $end
$var wire 14 / inst_word_in [13:0] $end
$var wire 1 - rst $end
$var wire 1 . start_layer $end
$var wire 4 0 stride [3:0] $end
$var wire 1 # relu_en $end
$var wire 1 $ pool_en $end
$var wire 4 1 layer_type [3:0] $end
$var wire 4 2 kernel_size [3:0] $end
$var parameter 32 3 INST_WIDTH $end
$var parameter 32 4 K_WIDTH $end
$var parameter 32 5 S_WIDTH $end
$var parameter 32 6 TYPE_WIDTH $end
$var reg 14 7 inst_reg [13:0] $end
$var reg 1 " start_decoded $end
$var reg 1 8 start_layer_d $end
$upscope $end
$scope begin $ivl_for_loop0 $end
$var integer 32 9 i [31:0] $end
$upscope $end
$scope task tog_rst $end
$upscope $end
$scope task tog_start $end
$upscope $end
$upscope $end
$enddefinitions $end
$comment Show the parameter values. $end
$dumpall
b100 6
b100 5
b100 4
b1110 3
b100 *
b100 )
b100 (
b1110 '
$end
#0
$dumpvars
b0 9
08
b0 7
b0 2
b0 1
b0 0
b0 /
x.
1-
b0 ,
0+
b0 &
b0 %
0$
0#
0"
b0 !
$end
#100000000
18
1"
1.
0-
1+
#200000000
0.
0+
#300000000
1$
0"
b1 7
1.
b1 ,
b1 /
b1 9
1+
#400000000
0.
0+
#500000000
1#
0$
b10 7
1.
b10 ,
b10 /
b10 9
1+
#600000000
0.
0+
#700000000
1$
b11 7
1.
b11 ,
b11 /
b11 9
1+
#800000000
0.
0+
#900000000
b1 !
b1 0
0#
0$
b100 7
1.
b100 ,
b100 /
b100 9
1+
#1000000000
0.
0+
#1100000000
1$
b101 7
1.
b101 ,
b101 /
b101 9
1+
#1200000000
0.
0+
#1300000000
1#
0$
b110 7
1.
b110 ,
b110 /
b110 9
1+
#1400000000
0.
0+
#1500000000
1$
b111 7
1.
b111 ,
b111 /
b111 9
1+
#1600000000
0.
0+
#1700000000
b10 !
b10 0
0#
0$
b1000 7
1.
b1000 ,
b1000 /
b1000 9
1+
#1800000000
0.
0+
#1900000000
1$
b1001 7
1.
b1001 ,
b1001 /
b1001 9
1+
#2000000000
0.
0+
#2100000000
1#
0$
b1010 7
1.
b1010 ,
b1010 /
b1010 9
1+
#2200000000
0.
0+
#2300000000
1$
b1011 7
1.
b1011 ,
b1011 /
b1011 9
1+
#2400000000
0.
0+
#2500000000
b11 !
b11 0
0#
0$
b1100 7
1.
b1100 ,
b1100 /
b1100 9
1+
#2600000000
0.
0+
#2700000000
1$
b1101 7
1.
b1101 ,
b1101 /
b1101 9
1+
#2800000000
0.
0+
#2900000000
1#
0$
b1110 7
1.
b1110 ,
b1110 /
b1110 9
1+
#3000000000
0.
0+
#3100000000
1$
b1111 7
1.
b1111 ,
b1111 /
b1111 9
1+
#3200000000
0.
0+
#3300000000
b100 !
b100 0
0#
0$
b10000 7
1.
b10000 ,
b10000 /
b10000 9
1+
#3400000000
0.
0+
#3500000000
1$
b10001 7
1.
b10001 ,
b10001 /
b10001 9
1+
#3600000000
0.
0+
#3700000000
1#
0$
b10010 7
1.
b10010 ,
b10010 /
b10010 9
1+
#3800000000
0.
0+
#3900000000
1$
b10011 7
1.
b10011 ,
b10011 /
b10011 9
1+
#4000000000
0.
0+
#4100000000
b101 !
b101 0
0#
0$
b10100 7
1.
b10100 ,
b10100 /
b10100 9
1+
#4200000000
0.
0+
#4300000000
1$
b10101 7
1.
b10101 ,
b10101 /
b10101 9
1+
#4400000000
0.
0+
#4500000000
1#
0$
b10110 7
1.
b10110 ,
b10110 /
b10110 9
1+
#4600000000
0.
0+
#4700000000
1$
b10111 7
1.
b10111 ,
b10111 /
b10111 9
1+
#4800000000
0.
0+
#4900000000
b110 !
b110 0
0#
0$
b11000 7
1.
b11000 ,
b11000 /
b11000 9
1+
#5000000000
0.
0+
#5100000000
1$
b11001 7
1.
b11001 ,
b11001 /
b11001 9
1+
#5200000000
0.
0+
#5300000000
1#
0$
b11010 7
1.
b11010 ,
b11010 /
b11010 9
1+
#5400000000
0.
0+
#5500000000
1$
b11011 7
1.
b11011 ,
b11011 /
b11011 9
1+
#5600000000
0.
0+
#5700000000
b111 !
b111 0
0#
0$
b11100 7
1.
b11100 ,
b11100 /
b11100 9
1+
#5800000000
0.
0+
#5900000000
1$
b11101 7
1.
b11101 ,
b11101 /
b11101 9
1+
#6000000000
0.
0+
#6100000000
1#
0$
b11110 7
1.
b11110 ,
b11110 /
b11110 9
1+
#6200000000
0.
0+
#6300000000
1$
b11111 7
1.
b11111 ,
b11111 /
b11111 9
1+
#6400000000
0.
0+
#6500000000
b1000 !
b1000 0
0#
0$
b100000 7
1.
b100000 ,
b100000 /
b100000 9
1+
#6600000000
0.
0+
#6700000000
1$
b100001 7
1.
b100001 ,
b100001 /
b100001 9
1+
#6800000000
0.
0+
#6900000000
1#
0$
b100010 7
1.
b100010 ,
b100010 /
b100010 9
1+
#7000000000
0.
0+
#7100000000
1$
b100011 7
1.
b100011 ,
b100011 /
b100011 9
1+
#7200000000
0.
0+
#7300000000
b1001 !
b1001 0
0#
0$
b100100 7
1.
b100100 ,
b100100 /
b100100 9
1+
#7400000000
0.
0+
#7500000000
1$
b100101 7
1.
b100101 ,
b100101 /
b100101 9
1+
#7600000000
0.
0+
#7700000000
1#
0$
b100110 7
1.
b100110 ,
b100110 /
b100110 9
1+
#7800000000
0.
0+
#7900000000
1$
b100111 7
1.
b100111 ,
b100111 /
b100111 9
1+
#8000000000
0.
0+
#8100000000
b1010 !
b1010 0
0#
0$
b101000 7
1.
b101000 ,
b101000 /
b101000 9
1+
#8200000000
0.
0+
#8300000000
1$
b101001 7
1.
b101001 ,
b101001 /
b101001 9
1+
#8400000000
0.
0+
#8500000000
1#
0$
b101010 7
1.
b101010 ,
b101010 /
b101010 9
1+
#8600000000
0.
0+
#8700000000
1$
b101011 7
1.
b101011 ,
b101011 /
b101011 9
1+
#8800000000
0.
0+
#8900000000
b1011 !
b1011 0
0#
0$
b101100 7
1.
b101100 ,
b101100 /
b101100 9
1+
#9000000000
0.
0+
#9100000000
1$
b101101 7
1.
b101101 ,
b101101 /
b101101 9
1+
#9200000000
0.
0+
#9300000000
1#
0$
b101110 7
1.
b101110 ,
b101110 /
b101110 9
1+
#9400000000
0.
0+
#9500000000
1$
b101111 7
1.
b101111 ,
b101111 /
b101111 9
1+
#9600000000
0.
0+
#9700000000
b1100 !
b1100 0
0#
0$
b110000 7
1.
b110000 ,
b110000 /
b110000 9
1+
#9800000000
0.
0+
#9900000000
1$
b110001 7
1.
b110001 ,
b110001 /
b110001 9
1+
#10000000000
0.
0+
#10100000000
1#
0$
b110010 7
1.
b110010 ,
b110010 /
b110010 9
1+
#10200000000
0.
0+
#10300000000
1$
b110011 7
1.
b110011 ,
b110011 /
b110011 9
1+
#10400000000
0.
0+
#10500000000
b1101 !
b1101 0
0#
0$
b110100 7
1.
b110100 ,
b110100 /
b110100 9
1+
#10600000000
0.
0+
#10700000000
1$
b110101 7
1.
b110101 ,
b110101 /
b110101 9
1+
#10800000000
0.
0+
#10900000000
1#
0$
b110110 7
1.
b110110 ,
b110110 /
b110110 9
1+
#11000000000
0.
0+
#11100000000
1$
b110111 7
1.
b110111 ,
b110111 /
b110111 9
1+
#11200000000
0.
0+
#11300000000
b1110 !
b1110 0
0#
0$
b111000 7
1.
b111000 ,
b111000 /
b111000 9
1+
#11400000000
0.
0+
#11500000000
1$
b111001 7
1.
b111001 ,
b111001 /
b111001 9
1+
#11600000000
0.
0+
#11700000000
1#
0$
b111010 7
1.
b111010 ,
b111010 /
b111010 9
1+
#11800000000
0.
0+
#11900000000
1$
b111011 7
1.
b111011 ,
b111011 /
b111011 9
1+
#12000000000
0.
0+
#12100000000
b1111 !
b1111 0
0#
0$
b111100 7
1.
b111100 ,
b111100 /
b111100 9
1+
#12200000000
0.
0+
#12300000000
1$
b111101 7
1.
b111101 ,
b111101 /
b111101 9
1+
#12400000000
0.
0+
#12500000000
1#
0$
b111110 7
1.
b111110 ,
b111110 /
b111110 9
1+
#12600000000
0.
0+
#12700000000
1$
b111111 7
1.
b111111 ,
b111111 /
b111111 9
1+
#12800000000
0.
0+
#12900000000
b1 &
b1 2
b0 !
b0 0
0#
0$
b1000000 7
1.
b1000000 ,
b1000000 /
b1000000 9
1+
#13000000000
0.
0+
#13100000000
1$
b1000001 7
1.
b1000001 ,
b1000001 /
b1000001 9
1+
#13200000000
0.
0+
#13300000000
1#
0$
b1000010 7
1.
b1000010 ,
b1000010 /
b1000010 9
1+
#13400000000
0.
0+
#13500000000
1$
b1000011 7
1.
b1000011 ,
b1000011 /
b1000011 9
1+
#13600000000
0.
0+
#13700000000
b1 !
b1 0
0#
0$
b1000100 7
1.
b1000100 ,
b1000100 /
b1000100 9
1+
#13800000000
0.
0+
#13900000000
1$
b1000101 7
1.
b1000101 ,
b1000101 /
b1000101 9
1+
#14000000000
0.
0+
#14100000000
1#
0$
b1000110 7
1.
b1000110 ,
b1000110 /
b1000110 9
1+
#14200000000
0.
0+
#14300000000
1$
b1000111 7
1.
b1000111 ,
b1000111 /
b1000111 9
1+
#14400000000
0.
0+
#14500000000
b10 !
b10 0
0#
0$
b1001000 7
1.
b1001000 ,
b1001000 /
b1001000 9
1+
#14600000000
0.
0+
#14700000000
1$
b1001001 7
1.
b1001001 ,
b1001001 /
b1001001 9
1+
#14800000000
0.
0+
#14900000000
1#
0$
b1001010 7
1.
b1001010 ,
b1001010 /
b1001010 9
1+
#15000000000
0.
0+
#15100000000
1$
b1001011 7
1.
b1001011 ,
b1001011 /
b1001011 9
1+
#15200000000
0.
0+
#15300000000
b11 !
b11 0
0#
0$
b1001100 7
1.
b1001100 ,
b1001100 /
b1001100 9
1+
#15400000000
0.
0+
#15500000000
1$
b1001101 7
1.
b1001101 ,
b1001101 /
b1001101 9
1+
#15600000000
0.
0+
#15700000000
1#
0$
b1001110 7
1.
b1001110 ,
b1001110 /
b1001110 9
1+
#15800000000
0.
0+
#15900000000
1$
b1001111 7
1.
b1001111 ,
b1001111 /
b1001111 9
1+
#16000000000
0.
0+
#16100000000
b100 !
b100 0
0#
0$
b1010000 7
1.
b1010000 ,
b1010000 /
b1010000 9
1+
#16200000000
0.
0+
#16300000000
1$
b1010001 7
1.
b1010001 ,
b1010001 /
b1010001 9
1+
#16400000000
0.
0+
#16500000000
1#
0$
b1010010 7
1.
b1010010 ,
b1010010 /
b1010010 9
1+
#16600000000
0.
0+
#16700000000
1$
b1010011 7
1.
b1010011 ,
b1010011 /
b1010011 9
1+
#16800000000
0.
0+
#16900000000
b101 !
b101 0
0#
0$
b1010100 7
1.
b1010100 ,
b1010100 /
b1010100 9
1+
#17000000000
0.
0+
#17100000000
1$
b1010101 7
1.
b1010101 ,
b1010101 /
b1010101 9
1+
#17200000000
0.
0+
#17300000000
1#
0$
b1010110 7
1.
b1010110 ,
b1010110 /
b1010110 9
1+
#17400000000
0.
0+
#17500000000
1$
b1010111 7
1.
b1010111 ,
b1010111 /
b1010111 9
1+
#17600000000
0.
0+
#17700000000
b110 !
b110 0
0#
0$
b1011000 7
1.
b1011000 ,
b1011000 /
b1011000 9
1+
#17800000000
0.
0+
#17900000000
1$
b1011001 7
1.
b1011001 ,
b1011001 /
b1011001 9
1+
#18000000000
0.
0+
#18100000000
1#
0$
b1011010 7
1.
b1011010 ,
b1011010 /
b1011010 9
1+
#18200000000
0.
0+
#18300000000
1$
b1011011 7
1.
b1011011 ,
b1011011 /
b1011011 9
1+
#18400000000
0.
0+
#18500000000
b111 !
b111 0
0#
0$
b1011100 7
1.
b1011100 ,
b1011100 /
b1011100 9
1+
#18600000000
0.
0+
#18700000000
1$
b1011101 7
1.
b1011101 ,
b1011101 /
b1011101 9
1+
#18800000000
0.
0+
#18900000000
1#
0$
b1011110 7
1.
b1011110 ,
b1011110 /
b1011110 9
1+
#19000000000
0.
0+
#19100000000
1$
b1011111 7
1.
b1011111 ,
b1011111 /
b1011111 9
1+
#19200000000
0.
0+
#19300000000
b1000 !
b1000 0
0#
0$
b1100000 7
1.
b1100000 ,
b1100000 /
b1100000 9
1+
#19400000000
0.
0+
#19500000000
1$
b1100001 7
1.
b1100001 ,
b1100001 /
b1100001 9
1+
#19600000000
0.
0+
#19700000000
1#
0$
b1100010 7
1.
b1100010 ,
b1100010 /
b1100010 9
1+
#19800000000
0.
0+
#19900000000
1$
b1100011 7
1.
b1100011 ,
b1100011 /
b1100011 9
1+
#20000000000
0.
0+
#20100000000
b1001 !
b1001 0
0#
0$
b1100100 7
1.
b1100100 ,
b1100100 /
b1100100 9
1+
#20200000000
0.
0+
#20300000000
1$
b1100101 7
1.
b1100101 ,
b1100101 /
b1100101 9
1+
#20400000000
0.
0+
#20500000000
1#
0$
b1100110 7
1.
b1100110 ,
b1100110 /
b1100110 9
1+
#20600000000
0.
0+
#20700000000
1$
b1100111 7
1.
b1100111 ,
b1100111 /
b1100111 9
1+
#20800000000
0.
0+
#20900000000
b1010 !
b1010 0
0#
0$
b1101000 7
1.
b1101000 ,
b1101000 /
b1101000 9
1+
#21000000000
0.
0+
#21100000000
1$
b1101001 7
1.
b1101001 ,
b1101001 /
b1101001 9
1+
#21200000000
0.
0+
#21300000000
1#
0$
b1101010 7
1.
b1101010 ,
b1101010 /
b1101010 9
1+
#21400000000
0.
0+
#21500000000
1$
b1101011 7
1.
b1101011 ,
b1101011 /
b1101011 9
1+
#21600000000
0.
0+
#21700000000
b1011 !
b1011 0
0#
0$
b1101100 7
1.
b1101100 ,
b1101100 /
b1101100 9
1+
#21800000000
0.
0+
#21900000000
1$
b1101101 7
1.
b1101101 ,
b1101101 /
b1101101 9
1+
#22000000000
0.
0+
#22100000000
1#
0$
b1101110 7
1.
b1101110 ,
b1101110 /
b1101110 9
1+
#22200000000
0.
0+
#22300000000
1$
b1101111 7
1.
b1101111 ,
b1101111 /
b1101111 9
1+
#22400000000
0.
0+
#22500000000
b1100 !
b1100 0
0#
0$
b1110000 7
1.
b1110000 ,
b1110000 /
b1110000 9
1+
#22600000000
0.
0+
#22700000000
1$
b1110001 7
1.
b1110001 ,
b1110001 /
b1110001 9
1+
#22800000000
0.
0+
#22900000000
1#
0$
b1110010 7
1.
b1110010 ,
b1110010 /
b1110010 9
1+
#23000000000
0.
0+
#23100000000
1$
b1110011 7
1.
b1110011 ,
b1110011 /
b1110011 9
1+
#23200000000
0.
0+
#23300000000
b1101 !
b1101 0
0#
0$
b1110100 7
1.
b1110100 ,
b1110100 /
b1110100 9
1+
#23400000000
0.
0+
#23500000000
1$
b1110101 7
1.
b1110101 ,
b1110101 /
b1110101 9
1+
#23600000000
0.
0+
#23700000000
1#
0$
b1110110 7
1.
b1110110 ,
b1110110 /
b1110110 9
1+
#23800000000
0.
0+
#23900000000
1$
b1110111 7
1.
b1110111 ,
b1110111 /
b1110111 9
1+
#24000000000
0.
0+
#24100000000
b1110 !
b1110 0
0#
0$
b1111000 7
1.
b1111000 ,
b1111000 /
b1111000 9
1+
#24200000000
0.
0+
#24300000000
1$
b1111001 7
1.
b1111001 ,
b1111001 /
b1111001 9
1+
#24400000000
0.
0+
#24500000000
1#
0$
b1111010 7
1.
b1111010 ,
b1111010 /
b1111010 9
1+
#24600000000
0.
0+
#24700000000
1$
b1111011 7
1.
b1111011 ,
b1111011 /
b1111011 9
1+
#24800000000
0.
0+
#24900000000
b1111 !
b1111 0
0#
0$
b1111100 7
1.
b1111100 ,
b1111100 /
b1111100 9
1+
#25000000000
0.
0+
#25100000000
1$
b1111101 7
1.
b1111101 ,
b1111101 /
b1111101 9
1+
#25200000000
0.
0+
#25300000000
1#
0$
b1111110 7
1.
b1111110 ,
b1111110 /
b1111110 9
1+
#25400000000
0.
0+
#25500000000
1$
b1111111 7
1.
b1111111 ,
b1111111 /
b1111111 9
1+
#25600000000
0.
0+
#25700000000
b10 &
b10 2
b0 !
b0 0
0#
0$
b10000000 7
1.
b10000000 ,
b10000000 /
b10000000 9
1+
#25800000000
0.
0+
#25900000000
1$
b10000001 7
1.
b10000001 ,
b10000001 /
b10000001 9
1+
#26000000000
0.
0+
#26100000000
1#
0$
b10000010 7
1.
b10000010 ,
b10000010 /
b10000010 9
1+
#26200000000
0.
0+
#26300000000
1$
b10000011 7
1.
b10000011 ,
b10000011 /
b10000011 9
1+
#26400000000
0.
0+
#26500000000
b1 !
b1 0
0#
0$
b10000100 7
1.
b10000100 ,
b10000100 /
b10000100 9
1+
#26600000000
0.
0+
#26700000000
1$
b10000101 7
1.
b10000101 ,
b10000101 /
b10000101 9
1+
#26800000000
0.
0+
#26900000000
1#
0$
b10000110 7
1.
b10000110 ,
b10000110 /
b10000110 9
1+
#27000000000
0.
0+
#27100000000
1$
b10000111 7
1.
b10000111 ,
b10000111 /
b10000111 9
1+
#27200000000
0.
0+
#27300000000
b10 !
b10 0
0#
0$
b10001000 7
1.
b10001000 ,
b10001000 /
b10001000 9
1+
#27400000000
0.
0+
#27500000000
1$
b10001001 7
1.
b10001001 ,
b10001001 /
b10001001 9
1+
#27600000000
0.
0+
#27700000000
1#
0$
b10001010 7
1.
b10001010 ,
b10001010 /
b10001010 9
1+
#27800000000
0.
0+
#27900000000
1$
b10001011 7
1.
b10001011 ,
b10001011 /
b10001011 9
1+
#28000000000
0.
0+
#28100000000
b11 !
b11 0
0#
0$
b10001100 7
1.
b10001100 ,
b10001100 /
b10001100 9
1+
#28200000000
0.
0+
#28300000000
1$
b10001101 7
1.
b10001101 ,
b10001101 /
b10001101 9
1+
#28400000000
0.
0+
#28500000000
1#
0$
b10001110 7
1.
b10001110 ,
b10001110 /
b10001110 9
1+
#28600000000
0.
0+
#28700000000
1$
b10001111 7
1.
b10001111 ,
b10001111 /
b10001111 9
1+
#28800000000
0.
0+
#28900000000
b100 !
b100 0
0#
0$
b10010000 7
1.
b10010000 ,
b10010000 /
b10010000 9
1+
#29000000000
0.
0+
#29100000000
1$
b10010001 7
1.
b10010001 ,
b10010001 /
b10010001 9
1+
#29200000000
0.
0+
#29300000000
1#
0$
b10010010 7
1.
b10010010 ,
b10010010 /
b10010010 9
1+
#29400000000
0.
0+
#29500000000
1$
b10010011 7
1.
b10010011 ,
b10010011 /
b10010011 9
1+
#29600000000
0.
0+
#29700000000
b101 !
b101 0
0#
0$
b10010100 7
1.
b10010100 ,
b10010100 /
b10010100 9
1+
#29800000000
0.
0+
#29900000000
1$
b10010101 7
1.
b10010101 ,
b10010101 /
b10010101 9
1+
#30000000000
0.
0+
#30100000000
1#
0$
b10010110 7
1.
b10010110 ,
b10010110 /
b10010110 9
1+
#30200000000
0.
0+
#30300000000
1$
b10010111 7
1.
b10010111 ,
b10010111 /
b10010111 9
1+
#30400000000
0.
0+
#30500000000
b110 !
b110 0
0#
0$
b10011000 7
1.
b10011000 ,
b10011000 /
b10011000 9
1+
#30600000000
0.
0+
#30700000000
1$
b10011001 7
1.
b10011001 ,
b10011001 /
b10011001 9
1+
#30800000000
0.
0+
#30900000000
1#
0$
b10011010 7
1.
b10011010 ,
b10011010 /
b10011010 9
1+
#31000000000
0.
0+
#31100000000
1$
b10011011 7
1.
b10011011 ,
b10011011 /
b10011011 9
1+
#31200000000
0.
0+
#31300000000
b111 !
b111 0
0#
0$
b10011100 7
1.
b10011100 ,
b10011100 /
b10011100 9
1+
#31400000000
0.
0+
#31500000000
1$
b10011101 7
1.
b10011101 ,
b10011101 /
b10011101 9
1+
#31600000000
0.
0+
#31700000000
1#
0$
b10011110 7
1.
b10011110 ,
b10011110 /
b10011110 9
1+
#31800000000
0.
0+
#31900000000
1$
b10011111 7
1.
b10011111 ,
b10011111 /
b10011111 9
1+
#32000000000
0.
0+
#32100000000
b1000 !
b1000 0
0#
0$
b10100000 7
1.
b10100000 ,
b10100000 /
b10100000 9
1+
#32200000000
0.
0+
#32300000000
1$
b10100001 7
1.
b10100001 ,
b10100001 /
b10100001 9
1+
#32400000000
0.
0+
#32500000000
1#
0$
b10100010 7
1.
b10100010 ,
b10100010 /
b10100010 9
1+
#32600000000
0.
0+
#32700000000
1$
b10100011 7
1.
b10100011 ,
b10100011 /
b10100011 9
1+
#32800000000
0.
0+
#32900000000
b1001 !
b1001 0
0#
0$
b10100100 7
1.
b10100100 ,
b10100100 /
b10100100 9
1+
#33000000000
0.
0+
#33100000000
1$
b10100101 7
1.
b10100101 ,
b10100101 /
b10100101 9
1+
#33200000000
0.
0+
#33300000000
1#
0$
b10100110 7
1.
b10100110 ,
b10100110 /
b10100110 9
1+
#33400000000
0.
0+
#33500000000
1$
b10100111 7
1.
b10100111 ,
b10100111 /
b10100111 9
1+
#33600000000
0.
0+
#33700000000
b1010 !
b1010 0
0#
0$
b10101000 7
1.
b10101000 ,
b10101000 /
b10101000 9
1+
#33800000000
0.
0+
#33900000000
1$
b10101001 7
1.
b10101001 ,
b10101001 /
b10101001 9
1+
#34000000000
0.
0+
#34100000000
1#
0$
b10101010 7
1.
b10101010 ,
b10101010 /
b10101010 9
1+
#34200000000
0.
0+
#34300000000
1$
b10101011 7
1.
b10101011 ,
b10101011 /
b10101011 9
1+
#34400000000
0.
0+
#34500000000
b1011 !
b1011 0
0#
0$
b10101100 7
1.
b10101100 ,
b10101100 /
b10101100 9
1+
#34600000000
0.
0+
#34700000000
1$
b10101101 7
1.
b10101101 ,
b10101101 /
b10101101 9
1+
#34800000000
0.
0+
#34900000000
1#
0$
b10101110 7
1.
b10101110 ,
b10101110 /
b10101110 9
1+
#35000000000
0.
0+
#35100000000
1$
b10101111 7
1.
b10101111 ,
b10101111 /
b10101111 9
1+
#35200000000
0.
0+
#35300000000
b1100 !
b1100 0
0#
0$
b10110000 7
1.
b10110000 ,
b10110000 /
b10110000 9
1+
#35400000000
0.
0+
#35500000000
1$
b10110001 7
1.
b10110001 ,
b10110001 /
b10110001 9
1+
#35600000000
0.
0+
#35700000000
1#
0$
b10110010 7
1.
b10110010 ,
b10110010 /
b10110010 9
1+
#35800000000
0.
0+
#35900000000
1$
b10110011 7
1.
b10110011 ,
b10110011 /
b10110011 9
1+
#36000000000
0.
0+
#36100000000
b1101 !
b1101 0
0#
0$
b10110100 7
1.
b10110100 ,
b10110100 /
b10110100 9
1+
#36200000000
0.
0+
#36300000000
1$
b10110101 7
1.
b10110101 ,
b10110101 /
b10110101 9
1+
#36400000000
0.
0+
#36500000000
1#
0$
b10110110 7
1.
b10110110 ,
b10110110 /
b10110110 9
1+
#36600000000
0.
0+
#36700000000
1$
b10110111 7
1.
b10110111 ,
b10110111 /
b10110111 9
1+
#36800000000
0.
0+
#36900000000
b1110 !
b1110 0
0#
0$
b10111000 7
1.
b10111000 ,
b10111000 /
b10111000 9
1+
#37000000000
0.
0+
#37100000000
1$
b10111001 7
1.
b10111001 ,
b10111001 /
b10111001 9
1+
#37200000000
0.
0+
#37300000000
1#
0$
b10111010 7
1.
b10111010 ,
b10111010 /
b10111010 9
1+
#37400000000
0.
0+
#37500000000
1$
b10111011 7
1.
b10111011 ,
b10111011 /
b10111011 9
1+
#37600000000
0.
0+
#37700000000
b1111 !
b1111 0
0#
0$
b10111100 7
1.
b10111100 ,
b10111100 /
b10111100 9
1+
#37800000000
0.
0+
#37900000000
1$
b10111101 7
1.
b10111101 ,
b10111101 /
b10111101 9
1+
#38000000000
0.
0+
#38100000000
1#
0$
b10111110 7
1.
b10111110 ,
b10111110 /
b10111110 9
1+
#38200000000
0.
0+
#38300000000
1$
b10111111 7
1.
b10111111 ,
b10111111 /
b10111111 9
1+
#38400000000
0.
0+
#38500000000
b11 &
b11 2
b0 !
b0 0
0#
0$
b11000000 7
1.
b11000000 ,
b11000000 /
b11000000 9
1+
#38600000000
0.
0+
#38700000000
1$
b11000001 7
1.
b11000001 ,
b11000001 /
b11000001 9
1+
#38800000000
0.
0+
#38900000000
1#
0$
b11000010 7
1.
b11000010 ,
b11000010 /
b11000010 9
1+
#39000000000
0.
0+
#39100000000
1$
b11000011 7
1.
b11000011 ,
b11000011 /
b11000011 9
1+
#39200000000
0.
0+
#39300000000
b1 !
b1 0
0#
0$
b11000100 7
1.
b11000100 ,
b11000100 /
b11000100 9
1+
#39400000000
0.
0+
#39500000000
1$
b11000101 7
1.
b11000101 ,
b11000101 /
b11000101 9
1+
#39600000000
0.
0+
#39700000000
1#
0$
b11000110 7
1.
b11000110 ,
b11000110 /
b11000110 9
1+
#39800000000
0.
0+
#39900000000
1$
b11000111 7
1.
b11000111 ,
b11000111 /
b11000111 9
1+
#40000000000
0.
0+
#40100000000
b10 !
b10 0
0#
0$
b11001000 7
1.
b11001000 ,
b11001000 /
b11001000 9
1+
#40200000000
0.
0+
#40300000000
1$
b11001001 7
1.
b11001001 ,
b11001001 /
b11001001 9
1+
#40400000000
0.
0+
#40500000000
1#
0$
b11001010 7
1.
b11001010 ,
b11001010 /
b11001010 9
1+
#40600000000
0.
0+
#40700000000
1$
b11001011 7
1.
b11001011 ,
b11001011 /
b11001011 9
1+
#40800000000
0.
0+
#40900000000
b11 !
b11 0
0#
0$
b11001100 7
1.
b11001100 ,
b11001100 /
b11001100 9
1+
#41000000000
0.
0+
#41100000000
1$
b11001101 7
1.
b11001101 ,
b11001101 /
b11001101 9
1+
#41200000000
0.
0+
