archive/t01_ai_mc_fifo.sv
`default_nettype none
/////////////////////////////////////////////////////////////////
// HEADER 
//
// Module : t01_ai_mc_fifo 
// Description : First-in, first-out 
// stores data in the order that ensures the first data written 
//           is the first data read 
// 
//
/////////////////////////////////////////////////////////////////
module t01_ai_mc_fifo #(
    parameter int DATA_W = 32, // width of each word
    parameter int DEPTH = 16, // number of entries
    parameter int ADDR_W = $clog2(DEPTH) // bits to index DEPTH 
)(
    input logic clk, rst, 

    // write & read interface 
    input logic wr_en, rd_en, // asser to engueue/dequeue when not full/not empty 
    input logic [DATA_W-1:0] wr_data, // data in 
    output logic [DATA_W-1:0] rd_data, // data out 
    output logic full, empty // no more room/no data to read 
); 
    logic [DATA_W-1:0] mem [0:DEPTH-1]; // memory array 
    logic [ADDR_W:0] wr_ptr, rd_ptr; // pointers with extra MSB for full/empty distinction 

    assign rd_data = mem[rd_ptr[ADDR_W-1:0]]; // read operation 
    assign full = (wr_ptr[ADDR_W] != rd_ptr[ADDR_W]) && (wr_ptr[ADDR_W-1:0] == rd_ptr[ADDR_W-1:0]); // full when pointers match except for the MSB (wrapped once ahead)
    assign empty = (wr_ptr == rd_ptr); // empty when pointers are exactly the same 
    // pointer updates 
    always_ff @(posedge clk, posedge rst) begin 
        if (rst) begin 
            wr_ptr <= 0; 
            rd_ptr <= 0; 
        end else begin 
            if (wr_en && !full) begin 
                mem[wr_ptr[ADDR_W-1:0]] <= wr_data; // write operation 
                wr_ptr <= wr_ptr + 1; 
            end 

            if (rd_en && !empty) begin 
                rd_ptr <= rd_ptr + 1; 
            end 
        end 
    end 
endmodule

testbench/t01_ai_mc_fifo_tb.sv
`timescale 1ms/1us

module t01_ai_mc_fifo_tb #(
    parameter int DATA_W = 32, // width of each word
    parameter int DEPTH = 16, // number of entries
    parameter int ADDR_W = $clog2(DEPTH) // bits to index DEPTH 
);
    
    logic clk, rst;
    logic wr_en, rd_en; // asser to engueue/dequeue when not full/not empty 
    logic [DATA_W-1:0] wr_data; // data in 
    logic [DATA_W-1:0] rd_data; // data out 
    logic full, empty; // no more room/no data to read 
    
    t01_ai_mc_fifo fifo (.clk(clk), .rst(rst), .wr_en(wr_en), .rd_en(rd_en), .wr_data(wr_data), .rd_data(rd_data), .full(full), .empty(empty));

    task tog_rst();
      rst = 1; #2; 
      rst = 0; 
    endtask 


    initial clk = 0; 
    always clk = #1 ~clk; 

    initial begin 
        $dumpfile("waves/t01_ai_mc_fifo.vcd"); 
        $dumpvars(0, t01_ai_mc_fifo_tb); 

        wr_data = 'd444; 
        tog_rst(); 

        for (int i = 0; i <= 1; i++) begin 
            for (int j = 0; j <= 1; j++) begin 
                        wr_en = i[0];
                        #1;  
                        rd_en = j[0];
                        #1;  
            end
        end 
        #6; 
        $finish; 
    end
endmodule

waves/t01_ai_mc_fifo.vcd
$date
	Mon Jul 28 10:50:23 2025
$end
$version
	Icarus Verilog
$end
$timescale
	1us
$end
$scope module t01_ai_mc_fifo_tb $end
$var wire 32 ! rd_data [31:0] $end
$var wire 1 " full $end
$var wire 1 # empty $end
$var parameter 32 $ ADDR_W $end
$var parameter 32 % DATA_W $end
$var parameter 32 & DEPTH $end
$var reg 1 ' clk $end
$var reg 1 ( rd_en $end
$var reg 1 ) rst $end
$var reg 32 * wr_data [31:0] $end
$var reg 1 + wr_en $end
$scope module fifo $end
$var wire 1 ' clk $end
$var wire 1 " full $end
$var wire 32 , rd_data [31:0] $end
$var wire 1 ( rd_en $end
$var wire 1 ) rst $end
$var wire 32 - wr_data [31:0] $end
$var wire 1 + wr_en $end
$var wire 1 # empty $end
$var parameter 32 . ADDR_W $end
$var parameter 32 / DATA_W $end
$var parameter 32 0 DEPTH $end
$var reg 5 1 rd_ptr [4:0] $end
$var reg 5 2 wr_ptr [4:0] $end
$upscope $end
$scope begin $ivl_for_loop0 $end
$var integer 32 3 i [31:0] $end
$scope begin $ivl_for_loop1 $end
$var integer 32 4 j [31:0] $end
$upscope $end
$upscope $end
$scope task tog_rst $end
$upscope $end
$upscope $end
$enddefinitions $end
$comment Show the parameter values. $end
$dumpall
b10000 0
b100000 /
b100 .
b10000 &
b100000 %
b100 $
$end
#0
$dumpvars
b0 4
b0 3
b0 2
b0 1
b110111100 -
bx ,
x+
b110111100 *
1)
x(
0'
1#
0"
bx !
$end
#1000
1'
#2000
0'
0+
0)
#3000
1'
0(
#4000
0'
b1 4
#5000
1'
1(
#6000
0'
1+
b1 3
b0 4
#7000
0#
b1 2
b110111100 !
b110111100 ,
1'
0(
#8000
0'
b1 4
#9000
b1 1
b10 2
1'
1(
#10000
0'
b10 3
b10 4
#11000
b10 1
b11 2
1'
#12000
0'
#13000
b11 1
b100 2
1'
#14000
0'
#15000
b100 1
b101 2
1'
