archive/t01_ai_mc_agu.sv
`default_nettype none
/////////////////////////////////////////////////////////////////
// HEADER 
//
// Module : t01_ai_mc_agu  
// Description : Address Generator for Memory Controller:
//                 - Latches base address & length on cmd_valid  
//                 - Streams out one address per beat, incrementing by BEAT_BYTES  
//                 - Asserts gen_last on the final beat
//
/////////////////////////////////////////////////////////////////
module t01_ai_mc_agu #(
    parameter int ADDR_W = 32, // width of the address bus 
    parameter int LEN_W = 16, // width of the length (in beats)
    parameter int BEAT_BYTES = 4 // bytes per burst beat 
)(
    input logic clk, rst, 
    
    // from command interface 
    input logic cmd_valid, cmd_ready, // 1 cycle pulse 
    input logic [ADDR_W-1:0] cmd_addr, // base address of the burst 
    input logic [LEN_W-1:0] cmd_len, // number of beats to generate 

    // to burst scheduler 
    output logic gen_valid, //gen_ready, // back-pressure from PHY!! 
    output logic [ADDR_W-1:0] gen_addr, // burrent beat's address 
    output logic gen_last 
); 

    logic active; // in the middle of a burst 
    logic [ADDR_W-1:0] base_addr; // latched base address 
    logic [LEN_W-1:0] beats_total, beats_cnt; // latched beat coumt, index 

    assign gen_valid = active; // valid during a burst
    assign gen_addr = base_addr + (beats_cnt * BEAT_BYTES); // current beat's address computation 
    assign gen_last = active && (beats_cnt == beats_total - 'd1); // final beat 
    // latch the command on cmd_valid 
    always_ff @(posedge clk, posedge rst) begin 
        if (rst) begin 
            active <= 0; 
            base_addr <= 0; 
            beats_total <= 0; 
            beats_cnt <= 0; 
        end else if (cmd_valid && cmd_ready) begin 
            active <= 1'b1; 
            base_addr <= cmd_addr;
            beats_total <= cmd_len; 
            beats_cnt <= beats_cnt + 'd1; 
        end else if (active && cmd_valid && cmd_ready && gen_last) begin 
            active <= 0; // finish the last beat 
        end 
    end
endmodule

testbench/t01_ai_mc_agu_tb.sv
`timescale 1ms/1us

module t01_ai_mc_agu_tb #(
    parameter int ADDR_W = 32, // width of the address bus 
    parameter int LEN_W = 16, // width of the length (in beats)
    parameter int BEAT_BYTES = 4 // bytes per burst beat 
);
    
    logic clk, rst;
    logic gen_last;
    logic [ADDR_W-1:0] cmd_addr, gen_addr;
    logic [LEN_W-1:0] cmd_len;
    logic cmd_ready, gen_ready;
    logic cmd_valid, gen_valid;
    
    t01_ai_mc_agu pipeline_controller (.clk(clk), .rst(rst), .cmd_valid(cmd_valid), .cmd_ready(cmd_ready), .cmd_addr(cmd_addr), .cmd_len(cmd_len), .gen_valid(gen_valid), .gen_addr(gen_addr), .gen_last);

    task tog_rst();
      rst = 1; #2; 
      rst = 0; 
    endtask 


    initial clk = 0; 
    always clk = #1 ~clk; 

    initial begin 
        $dumpfile("waves/t01_ai_mc_agu.vcd"); 
        $dumpvars(0, t01_ai_mc_agu_tb); 

        cmd_addr = 'd444; cmd_len = 'd4; 
        tog_rst(); 

        for (int i = 0; i <= 1; i++) begin 
            for (int j = 0; j <= 1; j++) begin 
                        cmd_valid = i[0];
                        #1;  
                        cmd_ready = j[0];
                        #1;  
            end
        end 
        #6; 
        $finish; 
    end
endmodule

waves/t01_ai_mc_agu.vcd
$date
	Mon Jul 28 09:50:21 2025
$end
$version
	Icarus Verilog
$end
$timescale
	1us
$end
$scope module t01_ai_mc_agu_tb $end
$var wire 1 ! gen_valid $end
$var wire 1 " gen_last $end
$var wire 32 # gen_addr [31:0] $end
$var parameter 32 $ ADDR_W $end
$var parameter 32 % BEAT_BYTES $end
$var parameter 32 & LEN_W $end
$var reg 1 ' clk $end
$var reg 32 ( cmd_addr [31:0] $end
$var reg 16 ) cmd_len [15:0] $end
$var reg 1 * cmd_ready $end
$var reg 1 + cmd_valid $end
$var reg 1 , rst $end
$scope module pipeline_controller $end
$var wire 1 ' clk $end
$var wire 32 - cmd_addr [31:0] $end
$var wire 16 . cmd_len [15:0] $end
$var wire 1 * cmd_ready $end
$var wire 1 + cmd_valid $end
$var wire 1 " gen_last $end
$var wire 1 ! gen_valid $end
$var wire 1 , rst $end
$var wire 32 / gen_addr [31:0] $end
$var parameter 32 0 ADDR_W $end
$var parameter 32 1 BEAT_BYTES $end
$var parameter 32 2 LEN_W $end
$var reg 1 3 active $end
$var reg 32 4 base_addr [31:0] $end
$var reg 16 5 beats_cnt [15:0] $end
$var reg 16 6 beats_total [15:0] $end
$upscope $end
$scope begin $ivl_for_loop0 $end
$var integer 32 7 i [31:0] $end
$scope begin $ivl_for_loop1 $end
$var integer 32 8 j [31:0] $end
$upscope $end
$upscope $end
$scope task tog_rst $end
$upscope $end
$upscope $end
$enddefinitions $end
$comment Show the parameter values. $end
$dumpall
b10000 2
b100 1
b100000 0
b10000 &
b100 %
b100000 $
$end
#0
$dumpvars
b0 8
b0 7
b0 6
b0 5
b0 4
03
b0 /
b100 .
b110111100 -
1,
x+
x*
b100 )
b110111100 (
0'
b0 #
0"
0!
$end
#1000
1'
#2000
0'
0+
0,
#3000
1'
0*
#4000
0'
b1 8
#5000
1'
1*
#6000
0'
1+
b1 7
b0 8
#7000
1'
0*
#8000
0'
b1 8
#9000
b1 5
b100 6
b111000000 #
b111000000 /
b110111100 4
1!
13
1'
1*
#10000
0'
b10 7
b10 8
#11000
b111000100 #
b111000100 /
b10 5
1'
#12000
0'
#13000
1"
b111001000 #
b111001000 /
b11 5
1'
#14000
0'
#15000
0"
b111001100 #
b111001100 /
b100 5
1'
