source/t01_ai_cu_sequencer.sv
`default_nettype none 

/////////////////////////////////////////////////////////////////
// HEADER 
//
// Module : t01_ai_cu_sequencer  
// Description : Control Unit Sequencer (Pipeline Controller)
// 
//
/////////////////////////////////////////////////////////////////

module t01_ai_cu_sequencer #(
    parameter int H_WIDTH = 10, // input height bits 
    parameter int W_WIDTH = 10, // input width bits 
    parameter int C_WIDTH = 8, // number of input channels 
    parameter int K_WIDTH = 4, // kernel size bits
    parameter int S_WIDTH = 4, // stride bits

    // derive output dims width at compile time 
    parameter int HOUT_WIDTH = H_WIDTH + 1,
    parameter int WOUT_WIDTH = W_WIDTH + 1 
)(
    input logic clk, rst, 
    input logic start_decoded, // from the instruction decoder 
    
    // configuration inputs 
    input logic [H_WIDTH-1:0] in_height, 
    input logic [W_WIDTH-1:0] in_width, 
    input logic [C_WIDTH-1:0] in_ch, 
    input logic [K_WIDTH-1:0] kernel_size, 
    input logic [S_WIDTH-1:0] stride, 
    input logic relu_en, pool_en,

    // outputs to datapath 
    output logic [HOUT_WIDTH-1:0] row_cnt, 
    output logic [WOUT_WIDTH-1:0] col_cnt, 
    output logic conv_valid, relu_valid, pool_valid, 

    // testbenches signals 
    output logic t1, 
    output logic [10:0] division, 
    // back to FSM 
    output logic seq_done
); 

    assign t1 = fill_cnt < kernel_size -1; 
    assign division = (in_height - {7'b0, kernel_size} / {7'b0, stride}) + 1;  
    
    // compute output dimensions at layer start
    logic [HOUT_WIDTH-1:0] H_out, W_out; 
    assign H_out = (in_height - {7'b0, kernel_size} / {7'b0, stride}) + 1; 
    assign W_out = (in_width - {7'b0, kernel_size} / {7'b0, stride}) + 1; 

    // nested counters over outputs 
    logic [$bits(H_out)-1:0] r_cnt, c_cnt; 
    assign row_cnt = r_cnt; 
    assign col_cnt = c_cnt;  

    // conv_valid generator 
    // assume pipeline_fill = kernel_size -1 
    logic [$clog2(16)-1:0] fill_cnt; 
    assign conv_valid = (fill_cnt == kernel_size -1) && !(r_cnt == H_out - 1 && c_cnt == W_out - 1); 

    // gated enalbles 
    assign relu_valid = conv_valid & relu_en; 
    // for 2*2 pooling - pending 
    wire row_edge = (r_cnt % 2 == 1); 
    wire col_edge = (c_cnt % 2 == 1); 
    assign pool_valid = conv_valid & pool_en & row_edge & col_edge; 

    // done pulse 
    assign seq_done = conv_valid && (r_cnt == H_out - 1) && (c_cnt == W_out - 1); 
    
    always_ff @(posedge clk, posedge rst) begin 
        if (rst) begin 
            {r_cnt, c_cnt} <= 0;
            fill_cnt <= 0; 
        end else if (start_decoded) begin 
            {r_cnt, c_cnt} <= 0; 
            fill_cnt <= 0; 
        end else if (fill_cnt < kernel_size -1) begin 
            fill_cnt <= fill_cnt + 1; 
        end else if (conv_valid) begin 
            if(c_cnt == W_out - 1) begin 
                c_cnt <= 0; 
                if (r_cnt == H_out - 1) begin 
                    r_cnt <= 0; 
                end else begin 
                    r_cnt <= r_cnt + 1; 
                end
            end else begin 
                    c_cnt <= c_cnt + 1; 
            end 
        end
    end


endmodule 

//     On start_decoded you load H_out/W_out and reset the counters + pipeline‐fill counter.

//     fill_cnt ramps up from 0 to K–1, modeling the systolic-array warm-up latency.

//     Once filled, conv_valid pulses each cycle as you step through all output positions.

//     relu_valid and pool_valid simply gate that stream by your per-layer flags and pooling boundary logic.

//     When you hit the last element, seq_done goes high for one cycle and your FSM moves on.

// This structure keeps the “when” logic nicely isolated in one module, with only a handful of inputs (configs + start) and outputs (address counters + valid strobes + done).

testbench/t01_ai_cu_sequencer_tb.sv
`timescale 1ms/1us

module t01_ai_cu_sequencer_tb #(
    parameter int H_WIDTH = 10, // input height bits 
    parameter int W_WIDTH = 10, // input width bits 
    parameter int C_WIDTH = 8, // number of input channels 
    parameter int K_WIDTH = 4, // kernel size bits
    parameter int S_WIDTH = 4, // stride bits

    // derive output dims width at compile time 
    parameter int HOUT_WIDTH = H_WIDTH + 1,
    parameter int WOUT_WIDTH = W_WIDTH + 1 
);
    
    logic clk, rst;
    logic start_decoded;
    logic [H_WIDTH-1:0] in_height;
    logic [W_WIDTH-1:0] in_width;
    logic [C_WIDTH-1:0] in_ch;
    logic [K_WIDTH-1:0] kernel_size;
    logic [S_WIDTH-1:0] stride;
    logic relu_en, pool_en;
    logic [HOUT_WIDTH-1:0] row_cnt;
    logic [WOUT_WIDTH-1:0] col_cnt;
    logic conv_valid, relu_valid, pool_valid;
    logic seq_done;  

    t01_ai_cu_sequencer pipeline_controller (.clk(clk), .rst(rst), .in_height(in_height), .in_width(in_width), .in_ch(in_ch), .kernel_size(kernel_size), .stride(stride), .relu_en(relu_en), .pool_en(pool_en), .row_cnt(row_cnt), .col_cnt(col_cnt), .conv_valid(conv_valid), .relu_valid(relu_valid), .pool_valid(pool_valid), .seq_done(seq_done));

    task tog_rst();
      rst = 1; #2; 
      rst = 0; 
    endtask 

    task tog_start(); 
        start_decoded = 1; #2; 
        start_decoded = 0; 
    endtask

    initial clk = 0; 
    always clk = #1 ~clk; 

    initial begin 
        $dumpfile("waves/t01_ai_cu_sequencer.vcd"); 
        $dumpvars(0, t01_ai_cu_sequencer_tb); 
        start_decoded = 0; 
        in_height = 'd10; in_width = 'd4;  
        in_ch = 'd4; kernel_size = 'd15; 
        stride = 'd5; 

        tog_rst(); 
        tog_start(); 

        #1; 
        for (int i = 0; i <= 1; i++) begin 
            for (int j = 0; j <= 1; j++) begin 
                relu_en = i[0]; 
                pool_en = j[0];
                #1;  
            end
        end 
        #50; 
        tog_start();
        #3; 
        $finish; 
    end
endmodule

waves/t01_ai_cu_sequencer.vcd
$date
	Thu Jul 24 11:15:48 2025
$end
$version
	Icarus Verilog
$end
$timescale
	1us
$end
$scope module t01_ai_cu_sequencer_tb $end
$var wire 1 ! seq_done $end
$var wire 11 " row_cnt [10:0] $end
$var wire 1 # relu_valid $end
$var wire 1 $ pool_valid $end
$var wire 1 % conv_valid $end
$var wire 11 & col_cnt [10:0] $end
$var parameter 32 ' C_WIDTH $end
$var parameter 32 ( HOUT_WIDTH $end
$var parameter 32 ) H_WIDTH $end
$var parameter 32 * K_WIDTH $end
$var parameter 32 + S_WIDTH $end
$var parameter 32 , WOUT_WIDTH $end
$var parameter 32 - W_WIDTH $end
$var reg 1 . clk $end
$var reg 8 / in_ch [7:0] $end
$var reg 10 0 in_height [9:0] $end
$var reg 10 1 in_width [9:0] $end
$var reg 4 2 kernel_size [3:0] $end
$var reg 1 3 pool_en $end
$var reg 1 4 relu_en $end
$var reg 1 5 rst $end
$var reg 1 6 start_decoded $end
$var reg 4 7 stride [3:0] $end
$scope module pipeline_controller $end
$var wire 1 . clk $end
$var wire 11 8 col_cnt [10:0] $end
$var wire 1 % conv_valid $end
$var wire 8 9 in_ch [7:0] $end
$var wire 10 : in_height [9:0] $end
$var wire 10 ; in_width [9:0] $end
$var wire 4 < kernel_size [3:0] $end
$var wire 1 3 pool_en $end
$var wire 1 $ pool_valid $end
$var wire 1 4 relu_en $end
$var wire 1 # relu_valid $end
$var wire 11 = row_cnt [10:0] $end
$var wire 1 5 rst $end
$var wire 1 ! seq_done $end
$var wire 1 > start_decoded $end
$var wire 4 ? stride [3:0] $end
$var wire 1 @ t1 $end
$var wire 1 A row_edge $end
$var wire 11 B division [10:0] $end
$var wire 1 C col_edge $end
$var wire 11 D W_out [10:0] $end
$var wire 11 E H_out [10:0] $end
$var parameter 32 F C_WIDTH $end
$var parameter 32 G HOUT_WIDTH $end
$var parameter 32 H H_WIDTH $end
$var parameter 32 I K_WIDTH $end
$var parameter 32 J S_WIDTH $end
$var parameter 32 K WOUT_WIDTH $end
$var parameter 32 L W_WIDTH $end
$var reg 11 M c_cnt [10:0] $end
$var reg 4 N fill_cnt [3:0] $end
$var reg 11 O r_cnt [10:0] $end
$upscope $end
$scope begin $ivl_for_loop0 $end
$var integer 32 P i [31:0] $end
$scope begin $ivl_for_loop1 $end
$var integer 32 Q j [31:0] $end
$upscope $end
$upscope $end
$scope task tog_rst $end
$upscope $end
$scope task tog_start $end
$upscope $end
$upscope $end
$enddefinitions $end
$comment Show the parameter values. $end
$dumpall
b1010 L
b1011 K
b100 J
b100 I
b1010 H
b1011 G
b1000 F
b1010 -
b1011 ,
b100 +
b100 *
b1010 )
b1011 (
b1000 '
$end
#0
$dumpvars
b0 Q
b0 P
b0 O
b0 N
b0 M
b1000 E
b10 D
0C
b1000 B
0A
1@
b101 ?
z>
b0 =
b1111 <
b100 ;
b1010 :
b100 9
b0 8
b101 7
06
15
x4
x3
b1111 2
b100 1
b1010 0
b100 /
0.
b0 &
0%
0$
0#
b0 "
0!
$end
#1000
1.
#2000
0.
16
05
#3000
b1 N
1.
#4000
0.
06
#5000
b10 N
1.
03
04
#6000
0.
13
b1 Q
#7000
b11 N
1.
03
14
b1 P
b0 Q
#8000
0.
13
b1 Q
#9000
b100 N
1.
b10 P
b10 Q
#10000
0.
#11000
b101 N
1.
#12000
0.
#13000
b110 N
1.
#14000
0.
#15000
b111 N
1.
#16000
0.
#17000
b1000 N
1.
#18000
0.
#19000
b1001 N
1.
#20000
0.
#21000
b1010 N
1.
#22000
0.
#23000
b1011 N
1.
#24000
0.
#25000
b1100 N
1.
#26000
0.
#27000
b1101 N
1.
#28000
0.
#29000
1#
1%
0@
b1110 N
1.
#30000
0.
#31000
1C
b1 &
b1 8
b1 M
1.
#32000
0.
#33000
1A
b1 "
b1 =
b1 O
0C
b0 &
b0 8
b0 M
1.
#34000
0.
#35000
1$
1C
b1 &
b1 8
b1 M
1.
#36000
0.
#37000
0$
0A
b10 "
b10 =
b10 O
0C
b0 &
b0 8
b0 M
1.
#38000
0.
#39000
1C
b1 &
b1 8
b1 M
1.
#40000
0.
#41000
1A
b11 "
b11 =
b11 O
0C
b0 &
b0 8
b0 M
1.
#42000
0.
#43000
1$
1C
b1 &
b1 8
b1 M
1.
#44000
0.
#45000
0$
0A
b100 "
b100 =
b100 O
0C
b0 &
b0 8
b0 M
1.
#46000
0.
#47000
1C
b1 &
b1 8
b1 M
1.
#48000
0.
#49000
1A
b101 "
b101 =
b101 O
0C
b0 &
b0 8
b0 M
1.
#50000
0.
#51000
1$
1C
b1 &
b1 8
b1 M
1.
#52000
0.
#53000
0$
0A
b110 "
b110 =
b110 O
0C
b0 &
b0 8
b0 M
1.
#54000
0.
#55000
1C
b1 &
b1 8
b1 M
1.
#56000
0.
#57000
1A
b111 "
b111 =
b111 O
0C
b0 &
b0 8
b0 M
1.
#58000
0.
#59000
0#
0%
0$
0!
1C
b1 &
b1 8
b1 M
1.
16
#60000
0.
#61000
1.
06
