source/update_ref.sv
`default_nettype none

/////////////////////////////////////////////////////////////////
// HEADER 
//
// Module : update_ref
// Description : Updates Tetris reference number 
// 
//
/////////////////////////////////////////////////////////////////

// import tetris_pkg::*;

module update_ref(
  input logic [4:0] row_i, 
  input logic [3:0] col_i, 
  input logic en, // enable update
  input move_t movement, 
  output logic [4:0] row_o, 
  output logic [3:0] col_o
);

  always_comb begin 
    row_o = row_i; 
    col_o = col_i; 

    if (en) begin 
      case (movement) 
        LEFT: begin 
          if (col_i == 'd9) begin 
            col_o = 0; 
          end else begin 
            col_o = col_i + 'd1; 
          end 
        end

        RIGHT: begin 
          if (col_i == 'd9) begin 
            col_o = 0; 
          end else begin 
            col_o = col_i - 'd1; 
          end 
        end

        DOWN: begin 
          row_o = row_i + 'd1; 
        end
      endcase
    end 
  end

endmodule

testbench/update_ref_tb.sv
`timescale 1ms/10ps

// import tetris_pkg::*; 

    typedef enum logic [4:0] {
        IDLE, // reset state 
        READY, // count down to start 
        NEW_BLOCK, // load new block 
        A1, // 011
        A2, 
        B1, // 101
        B2, 
        C1, // 111 
        C2, 
        D0, // 1001
        E1, // 1010 
        E2, 
        E3, 
        E4, 
        F1, // 1110 
        F2, 
        F3, 
        F4, 
        G1, // 10010
        G2, 
        G3, 
        G4, 
        EVAL, // evaluation 
        GAME_OVER // user run out of space 11000 
    } state_t; 

    typedef enum logic [2:0] {
        RIGHT, 
        LEFT, 
        ROR, // ROTATE RIGHT
        ROL, // ROTATE LEFT 
        DOWN
    } move_t; 

    typedef enum logic [2:0] {
        CL0, // BLACK   
        CL1, 
        CL2, 
        CL3, 
        CL4, 
        CL5, 
        CL6, 
        CL7
    } color_t; 


module update_ref_tb;
  logic [3:0] row_i, row_o; 
  logic [4:0] col_i, col_o; 
  logic en; 
  move_t movement; 
  update_ref fulladder (.row_i(row_i), .row_o(row_o), .col_i(col_i), .col_o(col_o), .en(en), .movement(movement));
  initial begin
    $dumpfile("waves/update_ref.vcd"); //change the vcd vile name to your source file name
    $dumpvars(0, update_ref_tb);
    
    en = 1'b1; 

    for (integer i = 0; i <= 20; i++) begin
      for (integer j = 0; j <= 9; j++) begin
        for (integer k = 0; k <= 4; k++) begin
        // set our input signals
        row_i = i[3:0]; col_i = j[4:0]; 
        
        if (k == 0) begin 
          #1; 
          movement = RIGHT; 
        end else if (k == 'd1) begin 
          #1; 
          movement = LEFT; 
        end else if (k == 'd2) begin 
          #1; 
          movement = ROR; 
        end else if (k == 'd3) begin 
          #1; 
          movement = ROL; 
        end else begin 
          #1; 
          movement = DOWN; 
        end 
        #1;
        // display inputs and outputs
        $display("row_i=\%b, col_i=\%b, movement=\%b, row_o=\%b, col_o=\%b", row_i, col_i, movement, row_o, col_o);
        end
      end
    end
  // finish the simulation
  #1 $finish;
  end
endmodule

waves/update_ref.vcd
$date
	Tue Jul  8 14:37:02 2025
$end
$version
	Icarus Verilog
$end
$timescale
	10ps
$end
$scope module update_ref_tb $end
$var wire 4 ! row_o [3:0] $end
$var wire 5 " col_o [4:0] $end
$var reg 5 # col_i [4:0] $end
$var reg 1 $ en $end
$var reg 3 % movement [2:0] $end
$var reg 4 & row_i [3:0] $end
$scope module fulladder $end
$var wire 4 ' col_i [3:0] $end
$var wire 1 $ en $end
$var wire 3 ( movement [2:0] $end
$var wire 5 ) row_i [4:0] $end
$var reg 4 * col_o [3:0] $end
$var reg 5 + row_o [4:0] $end
$upscope $end
$scope begin $ivl_for_loop0 $end
$var integer 32 , i [31:0] $end
$scope begin $ivl_for_loop1 $end
$var integer 32 - j [31:0] $end
$scope begin $ivl_for_loop2 $end
$var integer 32 . k [31:0] $end
$upscope $end
$upscope $end
$upscope $end
$upscope $end
$enddefinitions $end
$comment Show the parameter values. $end
$dumpall
$end
#0
$dumpvars
b0 .
b0 -
b0 ,
b0 +
b0 *
b0 )
bx (
b0 '
b0 &
bx %
1$
b0 #
b0 "
b0 !
$end
#100000000
b1111 "
b1111 *
b0 %
b0 (
#200000000
b1 .
#300000000
b1 "
b1 *
b1 %
b1 (
#400000000
b10 .
#500000000
b0 "
b0 *
b10 %
b10 (
#600000000
b11 .
#700000000
b11 %
b11 (
#800000000
b100 .
#900000000
b1 !
b1 +
b100 %
b100 (
#1000000000
b1 "
b1 *
b1 +
b1 '
b1 #
b1 -
b0 .
#1100000000
b0 !
b0 "
b0 *
b0 +
b0 %
b0 (
#1200000000
b1 .
#1300000000
b10 "
b10 *
b1 %
b1 (
#1400000000
b10 .
#1500000000
b1 "
b1 *
b10 %
b10 (
#1600000000
b11 .
#1700000000
b11 %
b11 (
#1800000000
b100 .
#1900000000
b1 !
b1 +
b100 %
b100 (
#2000000000
b10 "
b10 *
b1 +
b10 '
b10 #
b10 -
b0 .
#2100000000
b0 !
b1 "
b1 *
b0 +
b0 %
b0 (
#2200000000
b1 .
#2300000000
b11 "
b11 *
b1 %
b1 (
#2400000000
b10 .
#2500000000
b10 "
b10 *
b10 %
b10 (
#2600000000
b11 .
#2700000000
b11 %
b11 (
#2800000000
b100 .
#2900000000
b1 !
b1 +
b100 %
b100 (
#3000000000
b11 "
b11 *
b1 +
b11 '
b11 #
b11 -
b0 .
#3100000000
b0 !
b10 "
b10 *
b0 +
b0 %
b0 (
#3200000000
b1 .
#3300000000
b100 "
b100 *
b1 %
b1 (
#3400000000
b10 .
#3500000000
b11 "
b11 *
b10 %
b10 (
#3600000000
b11 .
#3700000000
b11 %
b11 (
#3800000000
b100 .
#3900000000
b1 !
b1 +
b100 %
b100 (
#4000000000
b100 "
b100 *
b1 +
b100 '
b100 #
b100 -
b0 .
#4100000000
b0 !
b11 "
b11 *
b0 +
b0 %
b0 (
#4200000000
b1 .
#4300000000
b101 "
b101 *
b1 %
b1 (
#4400000000
b10 .
#4500000000
b100 "
b100 *
b10 %
b10 (
#4600000000
b11 .
#4700000000
b11 %
b11 (
#4800000000
b100 .
#4900000000
b1 !
b1 +
b100 %
b100 (
#5000000000
b101 "
b101 *
b1 +
b101 '
b101 #
b101 -
b0 .
#5100000000
b0 !
b100 "
b100 *
b0 +
b0 %
b0 (
#5200000000
b1 .
#5300000000
b110 "
b110 *
b1 %
b1 (
#5400000000
b10 .
#5500000000
b101 "
b101 *
b10 %
b10 (
#5600000000
b11 .
#5700000000
b11 %
b11 (
#5800000000
b100 .
#5900000000
b1 !
b1 +
b100 %
b100 (
#6000000000
b110 "
b110 *
b1 +
b110 '
b110 #
b110 -
b0 .
#6100000000
b0 !
b101 "
b101 *
b0 +
b0 %
b0 (
#6200000000
b1 .
#6300000000
b111 "
b111 *
b1 %
b1 (
#6400000000
b10 .
#6500000000
b110 "
b110 *
b10 %
b10 (
#6600000000
b11 .
#6700000000
b11 %
b11 (
#6800000000
b100 .
#6900000000
b1 !
b1 +
b100 %
b100 (
#7000000000
b111 "
b111 *
b1 +
b111 '
b111 #
b111 -
b0 .
#7100000000
b0 !
b110 "
b110 *
b0 +
b0 %
b0 (
#7200000000
b1 .
#7300000000
b1000 "
b1000 *
b1 %
b1 (
#7400000000
b10 .
#7500000000
b111 "
b111 *
b10 %
b10 (
#7600000000
b11 .
#7700000000
b11 %
b11 (
#7800000000
b100 .
#7900000000
b1 !
b1 +
b100 %
b100 (
#8000000000
b1000 "
b1000 *
b1 +
b1000 '
b1000 #
b1000 -
b0 .
#8100000000
b0 !
b111 "
b111 *
b0 +
b0 %
b0 (
#8200000000
b1 .
#8300000000
b1001 "
b1001 *
b1 %
b1 (
#8400000000
b10 .
#8500000000
b1000 "
b1000 *
b10 %
b10 (
#8600000000
b11 .
#8700000000
b11 %
b11 (
#8800000000
b100 .
#8900000000
b1 !
b1 +
b100 %
b100 (
#9000000000
b1001 "
b1001 *
b1 +
b1001 '
b1001 #
b1001 -
b0 .
#9100000000
b0 !
b0 "
b0 *
b0 +
b0 %
b0 (
#9200000000
b1 .
#9300000000
b0 "
b0 *
b1 %
b1 (
#9400000000
b10 .
#9500000000
b1001 "
b1001 *
b10 %
b10 (
#9600000000
b11 .
#9700000000
b11 %
b11 (
#9800000000
b100 .
#9900000000
b1 !
b1 +
b100 %
b100 (
#10000000000
b0 "
b0 *
b10 !
b0 '
b10 +
b0 #
b1 )
b1 &
b1 ,
b0 -
b0 .
#10100000000
b1 !
b1111 "
b1111 *
b1 +
b0 %
b0 (
#10200000000
b1 .
#10300000000
b1 "
b1 *
b1 %
b1 (
#10400000000
b10 .
#10500000000
b0 "
b0 *
b10 %
b10 (
#10600000000
b11 .
#10700000000
b11 %
b11 (
#10800000000
b100 .
#10900000000
b10 !
b10 +
b100 %
b100 (
#11000000000
b1 "
b1 *
b10 +
b1 '
b1 #
b1 -
b0 .
#11100000000
b1 !
b0 "
b0 *
b1 +
b0 %
b0 (
#11200000000
b1 .
#11300000000
b10 "
b10 *
b1 %
b1 (
#11400000000
b10 .
#11500000000
b1 "
b1 *
b10 %
b10 (
#11600000000
b11 .
#11700000000
b11 %
b11 (
#11800000000
b100 .
#11900000000
b10 !
b10 +
b100 %
b100 (
#12000000000
b10 "
b10 *
b10 +
b10 '
b10 #
b10 -
b0 .
#12100000000
b1 !
b1 "
b1 *
b1 +
b0 %
b0 (
#12200000000
b1 .
#12300000000
b11 "
b11 *
b1 %
b1 (
#12400000000
b10 .
#12500000000
b10 "
b10 *
b10 %
b10 (
#12600000000
b11 .
#12700000000
b11 %
b11 (
#12800000000
b100 .
#12900000000
b10 !
b10 +
b100 %
b100 (
#13000000000
b11 "
b11 *
b10 +
b11 '
b11 #
b11 -
b0 .
#13100000000
b1 !
b10 "
b10 *
b1 +
b0 %
b0 (
#13200000000
b1 .
#13300000000
b100 "
b100 *
b1 %
b1 (
#13400000000
b10 .
#13500000000
b11 "
b11 *
b10 %
b10 (
#13600000000
b11 .
#13700000000
b11 %
b11 (
#13800000000
b100 .
#13900000000
b10 !
b10 +
b100 %
b100 (
#14000000000
b100 "
b100 *
b10 +
b100 '
b100 #
b100 -
b0 .
#14100000000
b1 !
b11 "
b11 *
b1 +
b0 %
b0 (
#14200000000
b1 .
#14300000000
b101 "
b101 *
b1 %
b1 (
#14400000000
b10 .
#14500000000
b100 "
b100 *
b10 %
b10 (
#14600000000
b11 .
#14700000000
b11 %
b11 (
#14800000000
b100 .
#14900000000
b10 !
b10 +
b100 %
b100 (
#15000000000
b101 "
b101 *
b10 +
b101 '
b101 #
b101 -
b0 .
#15100000000
b1 !
b100 "
b100 *
b1 +
b0 %
b0 (
#15200000000
b1 .
#15300000000
b110 "
b110 *
b1 %
b1 (
#15400000000
b10 .
#15500000000
b101 "
b101 *
b10 %
b10 (
#15600000000
b11 .
#15700000000
b11 %
b11 (
#15800000000
b100 .
#15900000000
b10 !
b10 +
b100 %
b100 (
#16000000000
b110 "
b110 *
b10 +
b110 '
b110 #
b110 -
b0 .
#16100000000
b1 !
b101 "
b101 *
b1 +
b0 %
b0 (
#16200000000
b1 .
#16300000000
b111 "
b111 *
b1 %
b1 (
#16400000000
b10 .
#16500000000
b110 "
b110 *
b10 %
b10 (
#16600000000
b11 .
#16700000000
b11 %
b11 (
#16800000000
b100 .
#16900000000
b10 !
b10 +
b100 %
b100 (
#17000000000
b111 "
b111 *
b10 +
b111 '
b111 #
b111 -
b0 .
#17100000000
b1 !
b110 "
b110 *
b1 +
b0 %
b0 (
#17200000000
b1 .
#17300000000
b1000 "
b1000 *
b1 %
b1 (
#17400000000
b10 .
#17500000000
b111 "
b111 *
b10 %
b10 (
#17600000000
b11 .
#17700000000
b11 %
b11 (
#17800000000
b100 .
#17900000000
b10 !
b10 +
b100 %
b100 (
#18000000000
b1000 "
b1000 *
b10 +
b1000 '
b1000 #
b1000 -
b0 .
#18100000000
b1 !
b111 "
b111 *
b1 +
b0 %
b0 (
#18200000000
b1 .
#18300000000
b1001 "
b1001 *
b1 %
b1 (
#18400000000
b10 .
#18500000000
b1000 "
b1000 *
b10 %
b10 (
#18600000000
b11 .
#18700000000
b11 %
b11 (
#18800000000
b100 .
#18900000000
b10 !
b10 +
b100 %
b100 (
#19000000000
b1001 "
b1001 *
b10 +
b1001 '
b1001 #
b1001 -
b0 .
#19100000000
b1 !
b0 "
b0 *
b1 +
b0 %
b0 (
#19200000000
b1 .
#19300000000
b0 "
b0 *
b1 %
b1 (
#19400000000
b10 .
#19500000000
b1001 "
b1001 *
b10 %
b10 (
#19600000000
b11 .
#19700000000
b11 %
b11 (
#19800000000
b100 .
#19900000000
b10 !
b10 +
b100 %
b100 (
#20000000000
b0 "
b0 *
b11 !
b0 '
b11 +
b0 #
b10 )
b10 &
b10 ,
b0 -
b0 .
#20100000000
b10 !
b1111 "
b1111 *
b10 +
b0 %
b0 (
#20200000000
b1 .
#20300000000
b1 "
b1 *
b1 %
b1 (
#20400000000
b10 .
#20500000000
b0 "
b0 *
b10 %
b10 (
#20600000000
b11 .
#20700000000
b11 %
b11 (
#20800000000
b100 .
#20900000000
b11 !
b11 +
b100 %
b100 (
#21000000000
b1 "
b1 *
b11 +
b1 '
b1 #
b1 -
b0 .
#21100000000
b10 !
b0 "
b0 *
b10 +
b0 %
b0 (
#21200000000
b1 .
#21300000000
b10 "
b10 *
b1 %
b1 (
#21400000000
b10 .
#21500000000
b1 "
b1 *
b10 %
b10 (
#21600000000
b11 .
#21700000000
b11 %
b11 (
#21800000000
b100 .
#21900000000
b11 !
b11 +
b100 %
b100 (
#22000000000
b10 "
b10 *
b11 +
b10 '
b10 #
b10 -
b0 .
#22100000000
b10 !
b1 "
b1 *
b10 +
b0 %
b0 (
#22200000000
b1 .
#22300000000
b11 "
b11 *
b1 %
b1 (
#22400000000
b10 .
#22500000000
b10 "
b10 *
b10 %
b10 (
#22600000000
b11 .
#22700000000
b11 %
b11 (
#22800000000
b100 .
#22900000000
b11 !
b11 +
b100 %
b100 (
#23000000000
b11 "
b11 *
b11 +
b11 '
b11 #
b11 -
b0 .
#23100000000
b10 !
b10 "
b10 *
b10 +
b0 %
b0 (
#23200000000
b1 .
#23300000000
b100 "
b100 *
b1 %
b1 (
#23400000000
b10 .
#23500000000
b11 "
b11 *
b10 %
b10 (
#23600000000
b11 .
#23700000000
b11 %
b11 (
#23800000000
b100 .
#23900000000
b11 !
b11 +
b100 %
b100 (
#24000000000
b100 "
b100 *
b11 +
b100 '
b100 #
b100 -
b0 .
#24100000000
b10 !
b11 "
b11 *
b10 +
b0 %
b0 (
#24200000000
b1 .
#24300000000
b101 "
b101 *
b1 %
b1 (
#24400000000
b10 .
#24500000000
b100 "
b100 *
b10 %
b10 (
#24600000000
b11 .
#24700000000
b11 %
b11 (
#24800000000
b100 .
#24900000000
b11 !
b11 +
b100 %
b100 (
#25000000000
b101 "
b101 *
b11 +
b101 '
b101 #
b101 -
b0 .
#25100000000
b10 !
b100 "
b100 *
b10 +
b0 %
b0 (
#25200000000
b1 .
#25300000000
b110 "
b110 *
b1 %
b1 (
#25400000000
b10 .
#25500000000
b101 "
b101 *
b10 %
b10 (
#25600000000
b11 .
#25700000000
b11 %
b11 (
#25800000000
b100 .
#25900000000
b11 !
b11 +
b100 %
b100 (
#26000000000
b110 "
b110 *
b11 +
b110 '
b110 #
b110 -
b0 .
#26100000000
b10 !
b101 "
b101 *
b10 +
b0 %
b0 (
#26200000000
b1 .
#26300000000
b111 "
b111 *
b1 %
b1 (
#26400000000
b10 .
#26500000000
b110 "
b110 *
b10 %
b10 (
#26600000000
b11 .
#26700000000
b11 %
b11 (
#26800000000
b100 .
#26900000000
b11 !
b11 +
b100 %
b100 (
#27000000000
b111 "
b111 *
b11 +
b111 '
b111 #
b111 -
b0 .
#27100000000
b10 !
b110 "
b110 *
b10 +
b0 %
b0 (
#27200000000
b1 .
#27300000000
b1000 "
b1000 *
b1 %
b1 (
#27400000000
b10 .
#27500000000
b111 "
b111 *
b10 %
b10 (
#27600000000
b11 .
#27700000000
b11 %
b11 (
#27800000000
b100 .
#27900000000
b11 !
b11 +
b100 %
b100 (
#28000000000
b1000 "
b1000 *
b11 +
b1000 '
b1000 #
b1000 -
b0 .
#28100000000
b10 !
b111 "
b111 *
b10 +
b0 %
b0 (
#28200000000
b1 .
#28300000000
b1001 "
b1001 *
b1 %
b1 (
#28400000000
b10 .
#28500000000
b1000 "
b1000 *
b10 %
b10 (
#28600000000
b11 .
#28700000000
b11 %
b11 (
#28800000000
b100 .
#28900000000
b11 !
b11 +
b100 %
b100 (
#29000000000
b1001 "
b1001 *
b11 +
b1001 '
b1001 #
b1001 -
b0 .
#29100000000
b10 !
b0 "
b0 *
b10 +
b0 %
b0 (
#29200000000
b1 .
#29300000000
b0 "
b0 *
b1 %
b1 (
#29400000000
b10 .
#29500000000
b1001 "
b1001 *
b10 %
b10 (
#29600000000
b11 .
#29700000000
b11 %
b11 (
#29800000000
b100 .
#29900000000
b11 !
b11 +
b100 %
b100 (
#30000000000
b0 "
b0 *
b100 !
b0 '
b100 +
b0 #
b11 )
b11 &
b11 ,
b0 -
b0 .
#30100000000
b11 !
b1111 "
b1111 *
b11 +
b0 %
b0 (
#30200000000
b1 .
#30300000000
b1 "
b1 *
b1 %
b1 (
#30400000000
b10 .
#30500000000
b0 "
b0 *
b10 %
b10 (
#30600000000
b11 .
#30700000000
b11 %
b11 (
#30800000000
b100 .
#30900000000
b100 !
b100 +
b100 %
b100 (
#31000000000
b1 "
b1 *
b100 +
b1 '
b1 #
b1 -
b0 .
#31100000000
b11 !
b0 "
b0 *
b11 +
b0 %
b0 (
#31200000000
b1 .
#31300000000
b10 "
b10 *
b1 %
b1 (
#31400000000
b10 .
#31500000000
b1 "
b1 *
b10 %
b10 (
#31600000000
b11 .
#31700000000
b11 %
b11 (
#31800000000
b100 .
#31900000000
b100 !
b100 +
b100 %
b100 (
#32000000000
b10 "
b10 *
b100 +
b10 '
b10 #
b10 -
b0 .
#32100000000
b11 !
b1 "
b1 *
b11 +
b0 %
b0 (
#32200000000
b1 .
#32300000000
b11 "
b11 *
b1 %
b1 (
#32400000000
b10 .
#32500000000
b10 "
b10 *
b10 %
b10 (
#32600000000
b11 .
#32700000000
b11 %
b11 (
#32800000000
b100 .
#32900000000
b100 !
b100 +
b100 %
b100 (
#33000000000
b11 "
b11 *
b100 +
b11 '
b11 #
b11 -
b0 .
#33100000000
b11 !
b10 "
b10 *
b11 +
b0 %
b0 (
#33200000000
b1 .
#33300000000
b100 "
b100 *
b1 %
b1 (
#33400000000
b10 .
#33500000000
b11 "
b11 *
b10 %
b10 (
#33600000000
b11 .
#33700000000
b11 %
b11 (
#33800000000
b100 .
#33900000000
b100 !
b100 +
b100 %
b100 (
#34000000000
b100 "
b100 *
b100 +
b100 '
b100 #
b100 -
b0 .
#34100000000
b11 !
b11 "
b11 *
b11 +
b0 %
b0 (
#34200000000
b1 .
#34300000000
b101 "
b101 *
b1 %
b1 (
#34400000000
b10 .
#34500000000
b100 "
b100 *
b10 %
b10 (
#34600000000
b11 .
#34700000000
b11 %
b11 (
#34800000000
b100 .
#34900000000
b100 !
b100 +
b100 %
b100 (
#35000000000
b101 "
b101 *
b100 +
b101 '
b101 #
b101 -
b0 .
#35100000000
b11 !
b100 "
b100 *
b11 +
b0 %
b0 (
#35200000000
b1 .
#35300000000
b110 "
b110 *
b1 %
b1 (
#35400000000
b10 .
#35500000000
b101 "
b101 *
b10 %
b10 (
#35600000000
b11 .
#35700000000
b11 %
b11 (
#35800000000
b100 .
#35900000000
b100 !
b100 +
b100 %
b100 (
#36000000000
b110 "
b110 *
b100 +
b110 '
b110 #
b110 -
b0 .
#36100000000
b11 !
b101 "
b101 *
b11 +
b0 %
b0 (
#36200000000
b1 .
#36300000000
b111 "
b111 *
b1 %
b1 (
#36400000000
b10 .
#36500000000
b110 "
b110 *
b10 %
b10 (
#36600000000
b11 .
#36700000000
b11 %
b11 (
#36800000000
b100 .
#36900000000
b100 !
b100 +
b100 %
b100 (
#37000000000
b111 "
b111 *
b100 +
b111 '
b111 #
b111 -
b0 .
#37100000000
b11 !
b110 "
b110 *
b11 +
b0 %
b0 (
#37200000000
b1 .
#37300000000
b1000 "
b1000 *
b1 %
b1 (
#37400000000
b10 .
#37500000000
b111 "
b111 *
b10 %
b10 (
#37600000000
b11 .
#37700000000
b11 %
b11 (
#37800000000
b100 .
#37900000000
b100 !
b100 +
b100 %
b100 (
#38000000000
b1000 "
b1000 *
b100 +
b1000 '
b1000 #
b1000 -
b0 .
#38100000000
b11 !
b111 "
b111 *
b11 +
b0 %
b0 (
#38200000000
b1 .
#38300000000
b1001 "
b1001 *
b1 %
b1 (
#38400000000
b10 .
#38500000000
b1000 "
b1000 *
b10 %
b10 (
#38600000000
b11 .
#38700000000
b11 %
b11 (
#38800000000
b100 .
#38900000000
b100 !
b100 +
b100 %
b100 (
#39000000000
b1001 "
b1001 *
b100 +
b1001 '
b1001 #
b1001 -
b0 .
#39100000000
b11 !
b0 "
b0 *
b11 +
b0 %
b0 (
#39200000000
b1 .
#39300000000
b0 "
b0 *
b1 %
b1 (
#39400000000
b10 .
#39500000000
b1001 "
b1001 *
b10 %
b10 (
#39600000000
b11 .
#39700000000
b11 %
b11 (
#39800000000
b100 .
#39900000000
b100 !
b100 +
b100 %
b100 (
#40000000000
b0 "
b0 *
b101 !
b0 '
b101 +
b0 #
b100 )
b100 &
b100 ,
b0 -
b0 .
#40100000000
b100 !
b1111 "
b1111 *
b100 +
b0 %
b0 (
#40200000000
b1 .
#40300000000
b1 "
b1 *
b1 %
b1 (
#40400000000
b10 .
#40500000000
b0 "
b0 *
b10 %
b10 (
#40600000000
b11 .
#40700000000
b11 %
b11 (
#40800000000
b100 .
#40900000000
b101 !
b101 +
b100 %
b100 (
#41000000000
b1 "
b1 *
b101 +
b1 '
b1 #
b1 -
b0 .
#41100000000
b100 !
b0 "
b0 *
b100 +
b0 %
b0 (
#41200000000
b1 .
#41300000000
b10 "
b10 *
b1 %
b1 (
#41400000000
b10 .
#41500000000
b1 "
b1 *
b10 %
b10 (
#41600000000
b11 .
#41700000000
b11 %
b11 (
#41800000000
b100 .
#41900000000
b101 !
b101 +
b100 %
b100 (
#42000000000
b10 "
b10 *
b101 +
b10 '
b10 #
b10 -
b0 .
#42100000000
b100 !
b1 "
b1 *
b100 +
b0 %
b0 (
#42200000000
b1 .
#42300000000
b11 "
b11 *
b1 %
b1 (
#42400000000
b10 .
#42500000000
b10 "
b10 *
b10 %
b10 (
#42600000000
b11 .
#42700000000
b11 %
b11 (
#42800000000
b100 .
#42900000000
b101 !
b101 +
b100 %
b100 (
#43000000000
b11 "
b11 *
b101 +
b11 '
b11 #
b11 -
b0 .
#43100000000
b100 !
b10 "
b10 *
b100 +
b0 %
b0 (
#43200000000
b1 .
#43300000000
b100 "
b100 *
b1 %
b1 (
#43400000000
b10 .
#43500000000
b11 "
b11 *
b10 %
b10 (
#43600000000
b11 .
#43700000000
b11 %
b11 (
#43800000000
b100 .
#43900000000
b101 !
b101 +
b100 %
b100 (
#44000000000
b100 "
b100 *
b101 +
b100 '
b100 #
b100 -
b0 .
#44100000000
b100 !
b11 "
b11 *
b100 +
b0 %
b0 (
#44200000000
b1 .
#44300000000
b101 "
b101 *
b1 %
b1 (
#44400000000
b10 .
#44500000000
b100 "
b100 *
b10 %
b10 (
#44600000000
b11 .
#44700000000
b11 %
b11 (
#44800000000
b100 .
#44900000000
b101 !
b101 +
b100 %
b100 (
#45000000000
b101 "
b101 *
b101 +
b101 '
b101 #
b101 -
b0 .
#45100000000
b100 !
b100 "
b100 *
b100 +
b0 %
b0 (
#45200000000
b1 .
#45300000000
b110 "
b110 *
b1 %
b1 (
#45400000000
b10 .
#45500000000
b101 "
b101 *
b10 %
b10 (
#45600000000
b11 .
#45700000000
b11 %
b11 (
#45800000000
b100 .
#45900000000
b101 !
b101 +
b100 %
b100 (
#46000000000
b110 "
b110 *
b101 +
b110 '
b110 #
b110 -
b0 .
#46100000000
b100 !
b101 "
b101 *
b100 +
b0 %
b0 (
#46200000000
b1 .
#46300000000
b111 "
b111 *
b1 %
b1 (
#46400000000
b10 .
#46500000000
b110 "
b110 *
b10 %
b10 (
#46600000000
b11 .
#46700000000
b11 %
b11 (
#46800000000
b100 .
#46900000000
b101 !
b101 +
b100 %
b100 (
#47000000000
b111 "
b111 *
b101 +
b111 '
b111 #
b111 -
b0 .
#47100000000
b100 !
b110 "
b110 *
b100 +
b0 %
b0 (
#47200000000
b1 .
#47300000000
b1000 "
b1000 *
b1 %
b1 (
#47400000000
b10 .
#47500000000
b111 "
b111 *
b10 %
b10 (
#47600000000
b11 .
#47700000000
b11 %
b11 (
#47800000000
b100 .
#47900000000
b101 !
b101 +
b100 %
b100 (
#48000000000
b1000 "
b1000 *
b101 +
b1000 '
b1000 #
b1000 -
b0 .
#48100000000
b100 !
b111 "
b111 *
b100 +
b0 %
b0 (
#48200000000
b1 .
#48300000000
b1001 "
b1001 *
b1 %
b1 (
#48400000000
b10 .
#48500000000
b1000 "
b1000 *
b10 %
b10 (
#48600000000
b11 .
#48700000000
b11 %
b11 (
#48800000000
b100 .
#48900000000
b101 !
b101 +
b100 %
b100 (
#49000000000
b1001 "
b1001 *
b101 +
b1001 '
b1001 #
b1001 -
b0 .
#49100000000
b100 !
b0 "
b0 *
b100 +
b0 %
b0 (
#49200000000
b1 .
#49300000000
b0 "
b0 *
b1 %
b1 (
#49400000000
b10 .
#49500000000
b1001 "
b1001 *
b10 %
b10 (
#49600000000
b11 .
#49700000000
b11 %
b11 (
#49800000000
b100 .
#49900000000
b101 !
b101 +
b100 %
b100 (
#50000000000
b0 "
b0 *
b110 !
b0 '
b110 +
b0 #
b101 )
b101 &
b101 ,
b0 -
b0 .
#50100000000
b101 !
b1111 "
b1111 *
b101 +
b0 %
b0 (
#50200000000
b1 .
#50300000000
b1 "
b1 *
b1 %
b1 (
#50400000000
b10 .
#50500000000
b0 "
b0 *
b10 %
b10 (
#50600000000
b11 .
#50700000000
b11 %
b11 (
#50800000000
b100 .
#50900000000
b110 !
b110 +
b100 %
b100 (
#51000000000
b1 "
b1 *
b110 +
b1 '
b1 #
b1 -
b0 .
#51100000000
b101 !
b0 "
b0 *
b101 +
b0 %
b0 (
#51200000000
b1 .
#51300000000
b10 "
b10 *
b1 %
b1 (
#51400000000
b10 .
#51500000000
b1 "
b1 *
b10 %
b10 (
#51600000000
b11 .
#51700000000
b11 %
b11 (
#51800000000
b100 .
#51900000000
b110 !
b110 +
b100 %
b100 (
#52000000000
b10 "
b10 *
b110 +
b10 '
b10 #
b10 -
b0 .
#52100000000
b101 !
b1 "
b1 *
b101 +
b0 %
b0 (
#52200000000
b1 .
#52300000000
b11 "
b11 *
b1 %
b1 (
#52400000000
b10 .
#52500000000
b10 "
b10 *
b10 %
b10 (
#52600000000
b11 .
#52700000000
b11 %
b11 (
#52800000000
b100 .
#52900000000
b110 !
b110 +
b100 %
b100 (
#53000000000
b11 "
b11 *
b110 +
b11 '
b11 #
b11 -
b0 .
#53100000000
b101 !
b10 "
b10 *
b101 +
b0 %
b0 (
#53200000000
b1 .
#53300000000
b100 "
b100 *
b1 %
b1 (
#53400000000
b10 .
#53500000000
b11 "
b11 *
b10 %
b10 (
#53600000000
b11 .
#53700000000
b11 %
b11 (
#53800000000
b100 .
#53900000000
b110 !
b110 +
b100 %
b100 (
#54000000000
b100 "
b100 *
b110 +
b100 '
b100 #
b100 -
b0 .
#54100000000
b101 !
b11 "
b11 *
b101 +
b0 %
b0 (
#54200000000
b1 .
#54300000000
b101 "
b101 *
b1 %
b1 (
#54400000000
b10 .
#54500000000
b100 "
b100 *
b10 %
b10 (
#54600000000
b11 .
#54700000000
b11 %
b11 (
#54800000000
b100 .
#54900000000
b110 !
b110 +
b100 %
b100 (
#55000000000
b101 "
b101 *
b110 +
b101 '
b101 #
b101 -
b0 .
#55100000000
b101 !
b100 "
b100 *
b101 +
b0 %
b0 (
#55200000000
b1 .
#55300000000
b110 "
b110 *
b1 %
b1 (
#55400000000
b10 .
#55500000000
b101 "
b101 *
b10 %
b10 (
#55600000000
b11 .
#55700000000
b11 %
b11 (
#55800000000
b100 .
#55900000000
b110 !
b110 +
b100 %
b100 (
#56000000000
b110 "
b110 *
b110 +
b110 '
b110 #
b110 -
b0 .
#56100000000
b101 !
b101 "
b101 *
b101 +
b0 %
b0 (
#56200000000
b1 .
#56300000000
b111 "
b111 *
b1 %
b1 (
#56400000000
b10 .
#56500000000
b110 "
b110 *
b10 %
b10 (
#56600000000
b11 .
#56700000000
b11 %
b11 (
#56800000000
b100 .
#56900000000
b110 !
b110 +
b100 %
b100 (
#57000000000
b111 "
b111 *
b110 +
b111 '
b111 #
b111 -
b0 .
#57100000000
b101 !
b110 "
b110 *
b101 +
b0 %
b0 (
#57200000000
b1 .
#57300000000
b1000 "
b1000 *
b1 %
b1 (
#57400000000
b10 .
#57500000000
b111 "
b111 *
b10 %
b10 (
#57600000000
b11 .
#57700000000
b11 %
b11 (
#57800000000
b100 .
#57900000000
b110 !
b110 +
b100 %
b100 (
#58000000000
b1000 "
b1000 *
b110 +
b1000 '
b1000 #
b1000 -
b0 .
#58100000000
b101 !
b111 "
b111 *
b101 +
b0 %
b0 (
#58200000000
b1 .
#58300000000
b1001 "
b1001 *
b1 %
b1 (
#58400000000
b10 .
#58500000000
b1000 "
b1000 *
b10 %
b10 (
#58600000000
b11 .
#58700000000
b11 %
b11 (
#58800000000
b100 .
#58900000000
b110 !
b110 +
b100 %
b100 (
#59000000000
b1001 "
b1001 *
b110 +
b1001 '
b1001 #
b1001 -
b0 .
#59100000000
b101 !
b0 "
b0 *
b101 +
b0 %
b0 (
#59200000000
b1 .
#59300000000
b0 "
b0 *
b1 %
b1 (
#59400000000
b10 .
#59500000000
b1001 "
b1001 *
b10 %
b10 (
#59600000000
b11 .
